Workbook

Sheet TC Count
B1: Module | C1: Type | D1: Type2 | E1: BGC | G1: CNG | I1: SCG | K1: CMP | M1: NYSEG | O1: RGE | Q1: UI
E2: iOS | F2: Android | G2: iOS | H2: Android | I2: iOS | J2: Android | K2: Android | L2: iOS | M2: Android | N2: iOS | O2: Android | P2: iOS | Q2: Android | R2: iOS
B3: Make a Payment Flow | C3: Regression | D3: Automated | E3: 91 | F3: 91 | G3: 87 | H3: 87 | I3: 87 | J3: 87 | K3: 227 | L3: 227 | M3: 52 | N3: 53 | O3: 53 | P3: 53 | Q3: 109 | R3: 111
B4: Manage Payment Method & Wallet | C4: Regression | D4: Automated | E4: 29 | F4: 29 | G4: 29 | H4: 29 | I4: 29 | J4: 29 | K4: 29 | L4: 29 | M4: 29 | N4: 29 | O4: 29 | P4: 29 | Q4: 29 | R4: 29
B5: Test Cases for Real Devices | C5: Regression | D5: Manual | E5: 42 | F5: 42 | G5: 42 | H5: 42 | I5: 43 | J5: 42 | K5: 42 | L5: 42 | M5: 42 | N5: 42 | O5: 42 | P5: 42 | Q5: 42 | R5: 42
B6: Log In | C6: QAT | D6: Automated | E6: 8 | F6: 8 | G6: 8 | H6: 8 | I6: 8 | J6: 9 | K6: 25 | L6: 25 | M6: 22 | N6: 17 | O6: 34 | P6: 17 | Q6: 24 | R6: 26
B7: Widget Status | C7: QAT | D7: Automated | E7: 8 | F7: 8 | G7: 8 | H7: 8 | I7: 8 | J7: 9 | K7: 7 | L7: 7 | M7: 7 | N7: 7 | O7: 7 | P7: 7 | Q7: 7 | R7: 7
B8: Dashboard | C8: QAT | D8: Automated | E8: 7 | F8: 7 | G8: 7 | H8: 7 | I8: 7 | J8: 7 | K8: 78 | L8: 78 | M8: 67 | N8: 67 | O8: 67 | P8: 67 | Q8: 67 | R8: 67 | T8: Billing&Payments | W8: My Preferences | AA8: My Accounts
B9: Bills & Payment | C9: QAT | D9: Automated | E9: 100 | F9: 100 | G9: 98 | H9: 98 | I9: 98 | J9: 98 | K9: 98 | L9: 98 | M9: 98 | N9: 98 | O9: 98 | P9: 98 | Q9: 96 | R9: 96 | T9: Make a Payment | W9: Push Notifications | AA9: Switch Accounts
B10: My Preferences | C10: QAT | D10: Automated | E10: 90 | F10: 92 | G10: 85 | H10: 85 | I10: 90 | J10: 90 | K10: 82 | L10: 82 | M10: 82 | N10: 82 | O10: 82 | P10: 82 | Q10: 82 | R10: 82 | T10: Enroll in e-Bill | W10: Alert Preferences | AA10: Make a Payment
B11: My Accounts | C11: QAT | D11: Automated | E11: 117 | F11: 117 | G11: 117 | H11: 117 | I11: 117 | J11: 117 | K11: 117 | L11: 117 | M11: 117 | N11: 117 | O11: 117 | P11: 117 | Q11: 117 | R11: 117 | T11: View Bill | W11: e-Bill enroll/de-enroll | AA11: My Preferences
B12: Outages | C12: QAT | D12: Automated | E12: 0 | F12: 0 | G12: 0 | H12: 0 | I12: 0 | J12: 0 | K12: 91 | L12: 91 | M12: 18 | N12: 18 | O12: 18 | P12: 18 | Q12: 52 | R12: 52 | T12: Download Bill | W12: Autopay enroll/de-enroll | AA12: My Profile
B13: Safety | C13: QAT | D13: Automated | E13: 37 | F13: 31 | G13: 31 | H13: 40 | I13: 31 | J13: 34 | K13: 0 | L13: 0 | M13: 31 | N13: 31 | O13: 31 | P13: 31 | Q13: 0 | R13: 0 | T13: Cancel Payment | W13: Budget billing enroll/de-enroll (no cmp) | AA13: Web Redirect
B14: Promo | C14: QAT | D14: Automated | E14: 9 | F14: 0 | G14: 9 | H14: 0 | I14: 9 | J14: 0 | K14: 25 | L14: 25 | M14: 7 | N14: 4 | O14: 4 | P14: 4 | Q14: 4 | R14: 4 | T14: View Bill/Payment History | W14: Operations ET enroll/de-enroll | AA14: Lookout
B15: Liferay Banner | C15: QAT | D15: Automated | E15: 17 | F15: 16 | G15: 10 | H15: 12 | I15: 14 | J15: 15 | K15: 10 | L15: 10 | M15: 10 | N15: 10 | O15: 10 | P15: 10 | Q15: 10 | R15: 10 | W15: Biometrics | AA15: Delete My Account
B16: Surveys | C16: QAT | D16: Automated | E16: 40 | F16: 35 | G16: 40 | H16: 40 | I16: 45 | J16: 37 | K16: 13 | L16: 13 | M16: 13 | N16: 13 | O16: 13 | P16: 13 | Q16: 13 | R16: 13 | W16: Cash only enroll
B17: End Meter Alerts | C17: QAT | D17: Manual | E17: 0 | F17: 0 | G17: 0 | H17: 0 | I17: 0 | J17: 0 | K17: 0 | L17: 0 | M17: 4 | N17: 4 | O17: 4 | P17: 4 | Q17: 0 | R17: 0
B18: Energy Manager | C18: QAT | D18: Manual | E18: 0 | F18: 0 | G18: 0 | H18: 0 | I18: 0 | J18: 0 | K18: 26 | L18: 26 | M18: 26 | N18: 26 | O18: 0 | P18: 0 | Q18: 26 | R18: 26
B19: Mandatory Update | C19: QAT | D19: Manual | E19: 4 | F19: 4 | G19: 4 | H19: 4 | I19: 4 | J19: 4 | K19: 4 | L19: 4 | M19: 4 | N19: 4 | O19: 4 | P19: 4 | Q19: 4 | R19: 4
B20: Non Mandatory Update | C20: QAT | D20: Manual | E20: 7 | F20: 7 | G20: 7 | H20: 7 | I20: 7 | J20: 7 | K20: 7 | L20: 7 | M20: 7 | N20: 7 | O20: 7 | P20: 7 | Q20: 7 | R20: 7
B21: Schedule Maintenance | C21: QAT | D21: Manual | E21: 3 | F21: 3 | G21: 4 | H21: 3 | I21: 3 | J21: 3 | K21: 3 | L21: 3 | M21: 3 | N21: 3 | O21: 3 | P21: 3 | Q21: 3 | R21: 3
E22: =SUM(E3:E21) -> 609 | F22: =SUM(F3:F21) -> 590 | G22: =SUM(G3:G21) -> 586 | H22: =SUM(H3:H21) -> 587 | I22: =SUM(I3:I21) -> 600 | J22: =SUM(J3:J21) -> 588 | K22: =SUM(K3:K21) -> 884 | L22: =SUM(L3:L21) -> 884 | ... R22: =SUM(R3:R21) -> 696 | T22: =SUM(E22:R22) -> 9216 | U22: << Total (Automated + Manual)
E24: =SUM(E3:E5) -> 162 | F24: =SUM(F3:F5) -> 162 | G24: =SUM(G3:G5) -> 158 | H24: =SUM(H3:H5) -> 158 | I24: =SUM(I3:I5) -> 159 | J24: =SUM(J3:J5) -> 158 | K24: =SUM(K3:K5) -> 298 | L24: =SUM(L3:L5) -> 298 | ... R24: =SUM(R3:R5) -> 182 | T24: =SUM(E24:R24) -> 2410 | U24: << Regression
E25: =SUM(E3:E16) -> 595 | F25: =SUM(F3:F16) -> 576 | G25: =SUM(G3:G16) -> 571 | H25: =SUM(H3:H16) -> 573 | I25: =SUM(I3:I16) -> 586 | J25: =SUM(J3:J16) -> 574 | K25: =SUM(K3:K16) -> 844 | L25: =SUM(L3:L16) -> 844 | ... R25: =SUM(R3:R16) -> 656 | T25: =SUM(E25:R25) -> 8847 | U25: << Automated (Reqgression + QAT)

Sheet Native Mobile Tests
A1: Key | B1: Name | C1: Assigned to | D1: Scripts | E1: Tests | F1: Status | G1: Comments | H1: Priority | I1: Feature | J1: OS | K1: OPCO | L1: Folder | M1: Coverage (Issues) | N1: Precondition | O1: Objective | P1: Test Script (Step-by-Step) - Step | Q1: Test Script (Step-by-Step) - Test Data | R1: Test Script (Step-by-Step) - Expected Result | S1: Column1
A2: MNDC-T1879 | B2: CNG - MNDC-39 - [IOS] - Login with wrong password | C2: Kevin | D2: Done | E2: Passed | F2: Complete | H2: =IF(I2="",200,VLOOKUP(I2,#REF!,2,FALSE)) -> #REF! | I2: Login | J2: IOS | K2: CNG | L2: /Login/CNG/IOS | M2: MNDC-39 | O2: Check if is validating the data informed in the login page fields | P2: I access login page *Then I should not be logged in and a message informing that the username or password is incorrect must be shown | R2: See the login fields and button *I should not be logged in, and I must see a validation message
A3: MNDC-T1877 | B3: CNG - MNDC-39 - [IOS] -Login with empty password field | C3: Kevin | D3: Done | E3: Passed | F3: Complete | H3: =IF(I3="",200,VLOOKUP(I3,#REF!,2,FALSE)) -> #REF! | I3: Login | J3: IOS | K3: CNG | L3: /Login/CNG/IOS | M3: MNDC-39 | O3: Check if is validating the data informed in the login page fields | P3: I access login page *Then the Log in button should be disabled | R3: See the login fields and button *The button should not be clickable if the mandatory information are not filled
A4: MNDC-T1878 | B4: CNG - MNDC-39 - [IOS] -Login with empty username field | C4: Kevin | D4: Done | E4: Passed | F4: Complete | H4: =IF(I4="",200,VLOOKUP(I4,#REF!,2,FALSE)) -> #REF! | I4: Login | J4: IOS | K4: CNG | L4: /Login/CNG/IOS | M4: MNDC-39 | O4: Check if is validating the data informed in the login page fields | P4: I access login page *Then the Log in button should be disabled | R4: See the login fields and button *The button should not be clickable if the mandatory information are not filled
A5: MNDC-T1961 | B5: CNG - MNDC-39 - [IOS] - Click on the tooltip in the username field in the login page to see tips about how to log in. | C5: Kevin | D5: Done | E5: Passed | F5: Complete | H5: =IF(I5="",200,VLOOKUP(I5,#REF!,2,FALSE)) -> #REF! | I5: Login | J5: IOS | K5: CNG | L5: /Login/CNG/IOS | O5: Check if is showing the message with the login instructions | P5: I access login page *Then I should see the instructions about the login | R5: See the login fields and buttons *The message should be as expected
A6: MNDC-T1881 | B6: CNG - MNDC-39 - [IOS] - Invalid/Incorrect username | C6: Kevin | D6: Done | E6: Passed | F6: Complete | H6: =IF(I6="",200,VLOOKUP(I6,#REF!,2,FALSE)) -> #REF! | I6: Login | J6: IOS | K6: CNG | L6: /Login/CNG/IOS | M6: MNDC-39 | O6: Check if the user is alowed to login correctly in the app | P6: I access login page *When I click on the Log in button Then I should not be logged in and a message informing that the username or password is incorrect must be shown | R6: See the login fields and button *The Log in button should be clickable
A7: MNDC-T1880 | B7: CNG - MNDC-39 - [IOS] - Successful login | C7: Kevin | D7: Done | E7: Passed | F7: Complete | H7: =IF(I7="",200,VLOOKUP(I7,#REF!,2,FALSE)) -> #REF! | I7: Login | J7: IOS | K7: CNG | L7: /Login/CNG/IOS | M7: MNDC-39 | O7: Check if is validating the data informed in the login page fields | P7: I access login page *Then I should be logged in and redirected to the Dashboard page | R7: See the login fields and button *I should be logged inand redirected to the dashboard page
A8: MNDC-T1883 | B8: CNG - MNDC-44 - [IOS] - Check splash screen display | C8: Kevin | D8: Done | E8: Passed | F8: Complete | H8: =IF(I8="",200,VLOOKUP(I8,#REF!,2,FALSE)) -> #REF! | I8: Login | J8: IOS | K8: CNG | L8: /Login/CNG/IOS | M8: MNDC-44 | O8: Validate if the logo is being correctly displayed | P8: When I access the app, then I should see the splash screen with the brand/OpCo logo | R8: The brand and the OpCo logo should be visible
A9: MNDC-T1882 | B9: MNDC-42 - CNG - [IOS] - Get message when offline | C9: Kevin | D9: Done | E9: Passed | F9: Complete | H9: =IF(I9="",200,VLOOKUP(I9,#REF!,2,FALSE)) -> #REF! | I9: Login | J9: IOS | K9: CNG | L9: /Login/CNG/IOS | M9: MNDC-42
A10: MNDC-T1932 | B10: CNG - MNDC-65 - [ANDROID] - Check splash screen display | C10: Jimmy | D10: Done | E10: Passed | F10: Done | H10: =IF(I10="",200,VLOOKUP(I10,#REF!,2,FALSE)) -> #REF! | I10: Login | J10: Android | K10: CNG | L10: /Login/CNG/ANDROID | M10: MNDC-65 | O10: Validate if the logo is being correctly displayed | P10: When I access the app, then I should see the splash screen with the brand/OpCo logo | R10: The brand and the OpCo logo should be visible
A11: MNDC-T1955 | B11: MNDC-62 - CNG - [ANDROID] - Click on the tooltip in the username field in the login page to see tips about how to log in. | C11: Jimmy | D11: Done | E11: Passed | F11: Done | H11: =IF(I11="",200,VLOOKUP(I11,#REF!,2,FALSE)) -> #REF! | I11: Login | J11: Android | K11: CNG | L11: /Login/CNG/ANDROID | O11: Check if is showing the message with the login instructions | P11: I access login page *Then I should see the instructions about the login | R11: See the login fields and buttons *The message should be as expected
A12: MNDC-T1928 | B12: MNDC-62 - CNG - [ANDROID] - Login with invalid username | C12: Jimmy | D12: Done | E12: Passed | F12: Done | H12: =IF(I12="",200,VLOOKUP(I12,#REF!,2,FALSE)) -> #REF! | I12: Login | J12: Android | K12: CNG | L12: /Login/CNG/ANDROID | M12: MNDC-62 | O12: Check if is validating the data informed in the login page fields | P12: Then the Log in button should be disabled *Then I should not be able to login | R12: The button should not be clickable if the mandatory information are not filled *The user should be allowed to login in app
A13: MNDC-T1927 | B13: MNDC-62 - CNG - [ANDROID] - Login with wrong password | C13: Jimmy | D13: Done | E13: Passed | F13: Done | H13: =IF(I13="",200,VLOOKUP(I13,#REF!,2,FALSE)) -> #REF! | I13: Login | J13: Android | K13: CNG | L13: /Login/CNG/ANDROID | M13: MNDC-62 | O13: Check if is validating the data informed in the login page fields | P13: I access login page *Then I should not be logged in and a message informing that the username or password is incorrect must be shown | R13: See the login fields and button *I should not be logged in, and I must see a validation message
A14: MNDC-T1929 | B14: MNDC-62 - CNG - [ANDROID] - Successful login | C14: Jimmy | D14: Done | E14: Passed | F14: Done | H14: =IF(I14="",200,VLOOKUP(I14,#REF!,2,FALSE)) -> #REF! | I14: Login | J14: Android | K14: CNG | L14: /Login/CNG/ANDROID | M14: MNDC-62 | O14: Check if the user is alowed to login correctly in the app | P14: I access login page *Then I should be able to login | R14: See the login fields and button *I should be able to login and land in home screen
A15: MNDC-T1925 | B15: MNDC-62 - CNG - [ANDROID] -Login with empty password field | C15: Jimmy | D15: Done | E15: Passed | F15: Done | H15: =IF(I15="",200,VLOOKUP(I15,#REF!,2,FALSE)) -> #REF! | I15: Login | J15: Android | K15: CNG | L15: /Login/CNG/ANDROID | M15: MNDC-62 | O15: Check if is validating the data informed in the login page fields | P15: I access login page *Then the Log in button should be disabled | R15: See the login fields and button *The button should not be clickable if the mandatory information are not filled
A16: MNDC-T1926 | B16: MNDC-62 - CNG - [ANDROID] -Login with empty username field | C16: Jimmy | D16: Done | E16: Passed | F16: Done | H16: =IF(I16="",200,VLOOKUP(I16,#REF!,2,FALSE)) -> #REF! | I16: Login | J16: Android | K16: CNG | L16: /Login/CNG/ANDROID | M16: MNDC-62 | O16: Check if is validating the data informed in the login page fields | P16: I access login page *Then the Log in button should be disabled | R16: See the login fields and button *The button should not be clickable if the mandatory information are not filled
A17: MNDC-T1931 | B17: MNDC-63 - CNG - [ANDROID] - Get message when offline | C17: Jimmy | D17: Done | E17: Passed | F17: Done | H17: =IF(I17="",200,VLOOKUP(I17,#REF!,2,FALSE)) -> #REF! | I17: Login | J17: Android | K17: CNG | L17: /Login/CNG/ANDROID | M17: MNDC-63 | O17: Checking the offline message validation | P17: When I try to navigate through the app I should see an offline message | R17: The system should show a message to the user informing that the dispositive is offline
A18: MNDC-T6801 | B18: CNG - IOS - MNDC-451 - Validate that the confirmation cancels when clicking on Go Back. | C18: Jimmy | D18: Done | E18: Passed | F18: Complete | H18: =IF(I18="",200,VLOOKUP(I18,#REF!,2,FALSE)) -> #REF! | I18: Manage Payment & Wallet | J18: IOS | K18: CNG | O18: Validate that the confirmation cancels when clicking on Go Back. | P18: Select an account with the "Payment Processing" status - or submit a payment in an account yourself. *Check that it should be back to the previuous screen ("Make a Payment").
A19: MNDC-T6800 | B19: CNG - IOS - MNDC-451 - Validate that the confirmation screen shows up. | C19: Jimmy | D19: Done | E19: Passed | F19: Complete | H19: =IF(I19="",200,VLOOKUP(I19,#REF!,2,FALSE)) -> #REF! | I19: Manage Payment & Wallet | J19: IOS | K19: CNG | O19: Validate that the confirmation screen shows up. | P19: Select an account with the "Payment Processing" status - or submit a payment in an account yourself. *Validate that the confirmation popup appear as it should.
A20: MNDC-T6803 | B20: CNG - IOS - MNDC-451 - Validate that the confirmation shows again when returning to the screen. | C20: Jimmy | D20: Done | E20: Passed | F20: Complete | H20: =IF(I20="",200,VLOOKUP(I20,#REF!,2,FALSE)) -> #REF! | I20: Manage Payment & Wallet | J20: IOS | K20: CNG | O20: Validate that the confirmation shows again when returning to the screen. | P20: Select an account with the "Payment Processing" status - or submit a payment in an account yourself. *Try to include the payment again and verify that the popup is shown again.
A21: MNDC-T6802 | B21: CNG - IOS - MNDC-451 - Validate that the payment goes through when continuing on the confirmation screen. | C21: Jimmy | D21: Done | E21: Passed | F21: Complete | H21: =IF(I21="",200,VLOOKUP(I21,#REF!,2,FALSE)) -> #REF! | I21: Manage Payment & Wallet | J21: IOS | K21: CNG | O21: Validate that the payment goes through when continuing on the confirmation screen. | P21: Select an account with the "Payment Processing" status - or submit a payment in an account yourself. *Check the Payments tab to verify that the additional payment was inserted.
A22: MNDC-T6804 | B22: CNG - IOS - MNDC-451 - Validate the confirmation popup's text. | C22: Jimmy | D22: Done | E22: Passed | F22: Complete | H22: =IF(I22="",200,VLOOKUP(I22,#REF!,2,FALSE)) -> #REF! | I22: Manage Payment & Wallet | J22: IOS | K22: CNG | O22: Validate the confirmation popup's text. | P22: Select an account with the "Payment Processing" status - or submit a payment in an account yourself. *Check that the text shown in the confirmation popup is the same as in the Story.
A23: MNDC-T6806 | B23: CNG - IOS - MNDC-451 - Validate the confirmation sceen on status other than Payment Processing | C23: Jimmy | D23: Done | E23: Passed | F23: Complete | H23: =IF(I23="",200,VLOOKUP(I23,#REF!,2,FALSE)) -> #REF! | I23: Manage Payment & Wallet | J23: IOS | K23: CNG | O23: Validate the confirmation sceen on status other than Payment Processing | P23: Select an account with a status other than "Payment Processing", such as Payment Past Due. *Check that the popup should NOT be shown and the payment shall go through, since the popup is for only additional payment.
A24: MNDC-T6805 | B24: CNG - IOS - MNDC-451 - Validation of the confirmation messages switching on and off the Remote Config. | C24: Jimmy | D24: Done | E24: Passed | F24: Complete | H24: =IF(I24="",200,VLOOKUP(I24,#REF!,2,FALSE)) -> #REF! | I24: Manage Payment & Wallet | J24: IOS | K24: CNG | O24: Validation of the confirmation messages switching on and off the Remote Config. | P24: Disable the warning popup in Remote config. *Try again and check that it should appear now.
A25: MNDC-T5960 | B25: CNG - MNDC-132 - Android - Kubra Add Failure Shows Error And No Add | C25: Jimmy | D25: Done | E25: Blocked | F25: Blocked | H25: =IF(I25="",200,VLOOKUP(I25,#REF!,2,FALSE)) -> #REF! | I25: Manage Payment & Wallet | J25: Android | K25: CNG | L25: /Manage Payment Method & Wallet/CNG/Android | N25: Kubra mock configured to return an error (e.g., 400/500) on add attempt. User on Kubra add flow. | O25: Verify the app handles a Kubra add-payment-method failure gracefully (error from Kubra) and does not add method to Payment methods list. | P25: 1. Open Payment Screen. *3. Observe Kubra/app behavior on failure and return to Payment methods screen (if user taps Back). | R25: 1. Kubra (or app) displays error message describing the failure. *3. After returning to Payment methods, the list remains unchanged.
A26: MNDC-T5958 | B26: CNG - MNDC-132 - Android - Open Kubra From AddBankAccount Button | C26: Jimmy | D26: Done | E26: Passed | F26: Done | H26: =IF(I26="",200,VLOOKUP(I26,#REF!,2,FALSE)) -> #REF! | I26: Manage Payment & Wallet | J26: Android | K26: CNG | L26: /Manage Payment Method & Wallet/CNG/Android | N26: User logged in on Payment methods screen. Firebase Remote Config "Add bank account" enabled. Network available. | O26: Verify that tapping the "Add bank account" button opens the Kubra screen. | P26: 1. Tap "Add bank account". *Add Credit/Debit card Payment method and complete the process | R26: App opens Kubra screen and shows loading state. *Credit/Debit card payment method is added successfully and seen in Payment method screen with Credit card icon
A27: MNDC-T5959 | B27: CNG - MNDC-132 - Android - Open Kubra From AddCard Button | C27: Jimmy | D27: Done | E27: Blocked | F27: Blocked | H27: =IF(I27="",200,VLOOKUP(I27,#REF!,2,FALSE)) -> #REF! | I27: Manage Payment & Wallet | J27: Android | K27: CNG | L27: /Manage Payment Method & Wallet/CNG/Android | N27: User logged in on Payment methods screen. Firebase Remote Config "Add credit and debit credit card" enabled. Network available. | O27: Verify that tapping the "Add credit and debit credit card" button opens the Kubra screen. | P27: 1. Tap "Add credit and debit credit card". *fill all required information and add the cc
A28: MNDC-T5957 | B28: CNG - MNDC-132 - Android - Open Kubra From ManageMyWallet Button | C28: Jimmy | D28: Done | E28: Passed | F28: Done | H28: =IF(I28="",200,VLOOKUP(I28,#REF!,2,FALSE)) -> #REF! | I28: Manage Payment & Wallet | J28: Android | K28: CNG | L28: /Manage Payment Method & Wallet/CNG/Android | N28: User is logged in and on Payment methods screen. Firebase Remote Config flag for "Manage my wallet" is enabled. Network available. Kubra external API reachable (or mock available). | O28: Verify that tapping the "Manage my wallet" button from the Payment methods screen opens the Kubra screen. | P28: 1. Tap "Manage my wallet". | R28: 1. App initiates navigation to Kubra (webview or external screen) and shows Kubra loading UI.
A29: MNDC-T7550 | B29: CNG - MNDC-1583 - Android - Checking CC's availability and display icon on adding a payment method. | H29: =IF(I29="",200,VLOOKUP(I29,#REF!,2,FALSE)) -> #REF! | I29: Manage Payment & Wallet | J29: Android | K29: CNG | L29: /Manage Payment Method & Wallet/CNG/Android | M29: MNDC-1583 | O29: Checking CC's availability and display icon on adding a payment method. | P29: From the Dashboard, advance to make a new payment; *Also check that, at the end of the CC/DC icon and name, the last four digits are shown as well and are consistente with the ones inserted before.
A30: MNDC-T7552 | B30: CNG - MNDC-1583 - Android - Checking CC's availability and display icon on changing payment methods. | H30: =IF(I30="",200,VLOOKUP(I30,#REF!,2,FALSE)) -> #REF! | I30: Manage Payment & Wallet | J30: Android | K30: CNG | L30: /Manage Payment Method & Wallet/CNG/Android | M30: MNDC-1583 | O30: Checking CC's availability and display icon on changing payment methods. | P30: From the Dashboard, advance to make a new payment; *Also check that, at the end of the CC/DC icon and name, the last four digits are shown as well.
A31: MNDC-T7551 | B31: CNG - MNDC-1583 - Android - Checking CC's availability and display icon on managing the wallet. | H31: =IF(I31="",200,VLOOKUP(I31,#REF!,2,FALSE)) -> #REF! | I31: Manage Payment & Wallet | J31: Android | K31: CNG | L31: /Manage Payment Method & Wallet/CNG/Android | M31: MNDC-1583 | O31: Checking CC's availability and display icon on managing the wallet. | P31: From the Dashboard, advance to make a new payment; *Also check that, at the end of the CC/DC icon and name, the last four digits are shown as well.
A32: MNDC-T7559 | B32: CNG - MNDC-1583 - iOS - Checking CC's availability and display icon on adding a payment method. | C32: Jimmy | D32: In Progress | F32: In Progress | H32: =IF(I32="",200,VLOOKUP(I32,#REF!,2,FALSE)) -> #REF! | I32: Manage Payment & Wallet | J32: IOS | K32: CNG | L32: /Manage Payment Method & Wallet/CNG/IOS | M32: MNDC-1583 | O32: Checking CC's availability and display icon on adding a payment method. | P32: From the Dashboard, advance to make a new payment; *Also check that, at the end of the CC/DC icon and name, the last four digits are shown as well and are consistente with the ones inserted before.
A33: MNDC-T7561 | B33: CNG - MNDC-1583 - iOS - Checking CC's availability and display icon on changing payment methods. | C33: Jimmy | D33: In Progress | F33: In Progress | H33: =IF(I33="",200,VLOOKUP(I33,#REF!,2,FALSE)) -> #REF! | I33: Manage Payment & Wallet | J33: IOS | K33: CNG | L33: /Manage Payment Method & Wallet/CNG/IOS | M33: MNDC-1583 | O33: Checking CC's availability and display icon on changing payment methods. | P33: From the Dashboard, advance to make a new payment; *Also check that, at the end of the CC/DC icon and name, the last four digits are shown as well.
A34: MNDC-T7560 | B34: CNG - MNDC-1583 - iOS - Checking CC's availability and display icon on managing the wallet. | C34: Jimmy | D34: In Progress | F34: In Progress | H34: =IF(I34="",200,VLOOKUP(I34,#REF!,2,FALSE)) -> #REF! | I34: Manage Payment & Wallet | J34: IOS | K34: CNG | L34: /Manage Payment Method & Wallet/CNG/IOS | M34: MNDC-1583 | O34: Checking CC's availability and display icon on managing the wallet. | P34: From the Dashboard, advance to make a new payment; *Also check that, at the end of the CC/DC icon and name, the last four digits are shown as well.
A35: MNDC-T5953 | B35: CNG - MNDC-258 - Android - API Error Handling | H35: =IF(I35="",200,VLOOKUP(I35,#REF!,2,FALSE)) -> #REF! | I35: Manage Payment & Wallet | J35: Android | K35: CNG | L35: /Manage Payment Method & Wallet/CNG/Android | N35: Ability to simulate API error or offline mode. | O35: Verify graceful handling of Payment Method API failures or network errors. | P35: 1. Trigger API failure scenario. *2. Open Manage payment method. | R35: 1. App receives API error or times out. *2. Screen shows an error message and a retry option or guidance; app does not crash.
A36: MNDC-T5954 | B36: CNG - MNDC-258 - Android - Default Payment Method Preselected Green Radio | C36: Jimmy | D36: Done | E36: Passed | F36: Done | H36: =IF(I36="",200,VLOOKUP(I36,#REF!,2,FALSE)) -> #REF! | I36: Manage Payment & Wallet | J36: Android | K36: CNG | L36: /Manage Payment Method & Wallet/CNG/Android | N36: Backend indicates a default method in API response. | O36: Verify the default payment method returned by API is preselected and shows a green radio. | P36: 1. Open Manage payment method. *Move around from one tab or screen to another and validate the above selected payment method is shown on both screens | R36: 1. Screen displays items. *User selected payment methods are shown until a new payment method is saved and selected on both Make a payment and Payment method screens
A37: MNDC-T5951 | B37: CNG - MNDC-258 - Android - Display Payment Methods List Populated From API | C37: Jimmy | D37: Done | E37: Passed | F37: Done | H37: =IF(I37="",200,VLOOKUP(I37,#REF!,2,FALSE)) -> #REF! | I37: Manage Payment & Wallet | J37: Android | K37: CNG | L37: /Manage Payment Method & Wallet/CNG/Android | N37: User logged in; network available; test account has N stored payment methods (N >= 1); API returns a valid list. | O37: Verify the "Manage payment method" screen displays the payment methods returned by the Payment Method API. | P37: 1. Open Manage payment method screen. *3. Inspect displayed list rows. | R37: 1. App issues Payment Method API request. *3. Screen shows one row per returned method with required labels/masked details and a radio control per row.
A38: MNDC-T5955 | B38: CNG - MNDC-258 - Android - Save Payment Method Redirect With Loader and New Selection | C38: Jimmy | D38: Done | E38: Passed | F38: Done | H38: =IF(I38="",200,VLOOKUP(I38,#REF!,2,FALSE)) -> #REF! | I38: Manage Payment & Wallet | J38: Android | K38: CNG | L38: /Manage Payment Method & Wallet/CNG/Android | N38: Save button visible (remote config ON); network available; backend saves default. | O38: Verify tapping "Save payment method" triggers loader, persists the new selection, and redirects to Make a Payment with that method preselected. | P38: 1. Tap Save payment method. *3. Observe redirection to Make a Payment. | R38: 1. Save flow starts and app calls backend (if applicable). *3. After success, app redirects to Make a Payment and the newly saved method is preselected.
A39: MNDC-T5956 | B39: CNG - MNDC-258 - Android - Save Without Change no Redirect With Loader | H39: =IF(I39="",200,VLOOKUP(I39,#REF!,2,FALSE)) -> #REF! | I39: Manage Payment & Wallet | J39: Android | K39: CNG | L39: /Manage Payment Method & Wallet/CNG/Android | N39: Save button visible and enabled. | O39: Verify tapping Save without changing selection still shows loader and redirects with the same method selected. | P39: 1. Tap Save payment method without altering selection. | R39: App redirects to Make a Payment with the same previously selected method.
A40: MNDC-T5952 | B40: CNG - MNDC-258 - Android - Supports payment methods added and are Scrollable | C40: Jimmy | D40: Done | E40: Passed | F40: Done | H40: =IF(I40="",200,VLOOKUP(I40,#REF!,2,FALSE)) -> #REF! | I40: Manage Payment & Wallet | J40: Android | K40: CNG | L40: /Manage Payment Method & Wallet/CNG/Android | N40: Test account prepopulated with added methods; device viewport smaller than list height. | O40: Verify the list supports all the payment methods added and is scrollable so all items can be viewed. | P40: 1. Open Manage payment method. *Validate the icons displayed for ACH and Credit/.Debit card payment methods | R40: 1. List initially shows the top portion of items. *For ACH account and Credit card separate icons are visible
A41: MNDC-T6874 | B41: CNG - MNDC-276 - IOS - Order Priority Influence (eBill → Autopay → budget billing) on Suggestions/Default Actions | C41: Kevin | D41: Done | E41: Passed | F41: Complete | H41: =IF(I41="",200,VLOOKUP(I41,#REF!,2,FALSE)) -> #REF! | I41: Manage Payment & Wallet | J41: IOS | K41: CNG | N41: - Conditions: Remote config may drive suggestion order; accounts have various combinations of enabled/disabled items. | O41: - Objective: Verify the system uses the order priority (ebill, autopay, budget billing) when presenting suggestions or default next steps on confirmation/failure screens. | P41: 1. For each scenario, perform a successful and failed payment and observe suggestion lists and default CTA ordering. | R41: - Suggestions and CTAs should prioritize eBill related actions first (if relevant), then Autopay actions, then Budget Billing suggestions. For example, if eBill is off, suggestion to enroll in eBill is shown above autopay suggestion.
A42: MNDC-T6872 | B42: CNG - MNDC-276 - IOS - Successful Payment: Confirmation Page Elements Present and Accurate | C42: Jimmy | D42: Done | E42: Passed | F42: Complete | H42: =IF(I42="",200,VLOOKUP(I42,#REF!,2,FALSE)) -> #REF! | I42: Manage Payment & Wallet | J42: IOS | K42: CNG | N42: - Conditions: Payment processed successfully in test environment (sandbox). Remote Config success-page keys present. | O42: - Objective: Verify that when payment request returns successful, the confirmation page displays: payment amount, payment date, status, reference number, account number (masked as required), and provides a back option. | P42: 1. Complete a payment that will be accepted by backend (simulate success). *3. Tap the back option. | R42: *- Expected result: Pass if all elements are present, values match the transaction, and back navigation works.
A43: MNDC-T6861 | B43: CNG - MNDC-279 - IOS - Workflow 1 - New ACH Payment with Bank Account Selected | C43: Kevin | D43: Done | E43: Passed | F43: Complete | H43: =IF(I43="",200,VLOOKUP(I43,#REF!,2,FALSE)) -> #REF! | I43: Manage Payment & Wallet | J43: IOS | K43: CNG | N43: Preconditions: User has no stored payment methods or chooses to add new. | O43: Objective: Validate new ACH payment flow with bank account selection and optional save to wallet. | P43: 1. Select "Bank Account" as payment method. *5. Click "Pay $XX" button. | R43: *If "Save payment method" checked User receives Confirmation of successful payment.
A44: MNDC-T6863 | B44: CNG - MNDC-279 - IOS - Workflow 2 - Existing ACH Payment - Confirmation Step UI Elements | C44: Kevin | D44: Done | E44: Passed | F44: Complete | H44: =IF(I44="",200,VLOOKUP(I44,#REF!,2,FALSE)) -> #REF! | I44: Manage Payment & Wallet | J44: IOS | K44: CNG | N44: Preconditions: User is on confirmation step after payment method selection. | O44: Objective: Validate confirmation step UI after selecting stored ACH payment method. | P44: 1. Observe static checkout component. *7. Click "Cancel" button and observe navigation. | R44: *"Remember my payment details" is defaulted to "On". - "Pay" button shows correct amount and proceeds to Step 3 on click. - "Cancel" button returns user to Step 3: Make a Payment page.
A45: MNDC-T6862 | B45: CNG - MNDC-279 - IOS - Workflow 2 - Existing ACH Payment (Remember Me) - Display Stored Payment Methods | C45: Kevin | D45: Done | E45: Passed | F45: Complete | H45: =IF(I45="",200,VLOOKUP(I45,#REF!,2,FALSE)) -> #REF! | I45: Manage Payment & Wallet | J45: IOS | K45: CNG | N45: Preconditions: User logged in with stored payment methods. | O45: Objective: Verify display and selection of stored ACH payment methods with last used on top. | P45: 1. Navigate to initial checkout page. *6. Verify Apple/Google Pay button is visible at the bottom. | R45: *All stored ACH Payment methods are visible with last used on top. - "Add Payment Method" button navigates to new payment flow (Workflow 1 or 3). Apple/Google Pay button is visible and functional.
A46: MNDC-T6864 | B46: CNG - MNDC-279 - IOS - Workflow 3 - New Credit/Debit Card Payment | C46: Jimmy | D46: Done | E46: Passed | F46: Complete | H46: =IF(I46="",200,VLOOKUP(I46,#REF!,2,FALSE)) -> #REF! | I46: Manage Payment & Wallet | J46: IOS | K46: CNG | N46: Preconditions: User has no stored card payment methods or chooses to add new. | O46: Objective: Validate new credit/debit card payment flow with optional save to wallet. | P46: 1. Select "Credit or Debit Card" as payment method. *5. Click "Pay $XX" button. | R46: *Payment details accepted and processed. - If "Save payment method" checked User receives Confirmation of successful payment.
A47: MNDC-T6865 | B47: CNG - MNDC-279 - IOS - Workflow 4 - Existing Credit/Debit Card Payment - Display Stored Payment Methods | C47: Kevin | D47: Done | E47: Passed | F47: Complete | H47: =IF(I47="",200,VLOOKUP(I47,#REF!,2,FALSE)) -> #REF! | I47: Manage Payment & Wallet | J47: IOS | K47: CNG | N47: Preconditions: User logged in with stored payment methods. | O47: Objective: Verify display and selection of stored credit/debit card payment methods with last used on top. | P47: 1. Navigate to initial checkout page. *6. Verify Apple/Google Pay button is visible at the bottom.
A48: MNDC-T6038 | B48: CNG - MNDC-356 - IOS - Kubra Add Failure Shows Error And No Add | C48: Kevin | D48: Done | E48: Passed | F48: Complete | H48: =IF(I48="",200,VLOOKUP(I48,#REF!,2,FALSE)) -> #REF! | I48: Manage Payment & Wallet | J48: IOS | K48: CNG | L48: /Manage Payment Method & Wallet/CNG/IOS | N48: Kubra mock configured to return an error (e.g., 400/500) on add attempt. User on Kubra add flow. | O48: Verify the app handles a Kubra add-payment-method failure gracefully (error from Kubra) and does not add method to Payment methods list. | P48: 1. Open Payment Screen. *3. Observe Kubra/app behavior on failure and return to Payment methods screen (if user taps Back). | R48: 1. Kubra (or app) displays error message describing the failure. *3. After returning to Payment methods, the list remains unchanged.
A49: MNDC-T6036 | B49: CNG - MNDC-356 - IOS - Open Kubra From AddBankAccount Button | C49: Kevin | D49: Done | E49: Passed | F49: Complete | H49: =IF(I49="",200,VLOOKUP(I49,#REF!,2,FALSE)) -> #REF! | I49: Manage Payment & Wallet | J49: IOS | K49: CNG | L49: /Manage Payment Method & Wallet/CNG/IOS | N49: User logged in on Payment methods screen. Firebase Remote Config "Add bank account" enabled. Network available. | O49: Verify that tapping the "Add bank account" button opens the Kubra screen. | P49: 1. Tap "Add bank account". *Add Credit card Payment method and complete the process | R49: App opens Kubra screen and shows loading state. *Credit/Debit card payment method is added successfully and seen in Payment method screen with Credit card icon
A50: MNDC-T6037 | B50: CNG - MNDC-356 - IOS - Open Kubra From AddCard Button | C50: Kevin | D50: Done | E50: Passed | F50: Complete | H50: =IF(I50="",200,VLOOKUP(I50,#REF!,2,FALSE)) -> #REF! | I50: Manage Payment & Wallet | J50: IOS | K50: CNG | L50: /Manage Payment Method & Wallet/CNG/IOS | N50: User logged in on Payment methods screen. Firebase Remote Config "Add credit and debit credit card" enabled. Network available. | O50: Verify that tapping the "Add credit and debit credit card" button opens the Kubra screen. | P50: 1. Tap "Add credit and debit credit card". | R50: Kubra screen displayed and external Kubra call initiated.
A51: MNDC-T6035 | B51: CNG - MNDC-356 - IOS - Open Kubra From ManageMyWallet Button | C51: Kevin | D51: Done | E51: Passed | F51: Complete | H51: =IF(I51="",200,VLOOKUP(I51,#REF!,2,FALSE)) -> #REF! | I51: Manage Payment & Wallet | J51: IOS | K51: CNG | L51: /Manage Payment Method & Wallet/CNG/IOS | N51: User is logged in and on Payment methods screen. Firebase Remote Config flag for "Manage my wallet" is enabled. Network available. Kubra external API reachable (or mock available). | O51: Verify that tapping the "Manage my wallet" button from the Payment methods screen opens the Kubra screen. | P51: 1. Tap "Manage my wallet". | R51: 1. App initiates navigation to Kubra (webview or external screen) and shows Kubra loading UI.
A52: MNDC-T6031 | B52: CNG - MNDC-390 - IOS - API Error Handling | C52: Jimmy | D52: No Auto | E52: No Auto | F52: No Auto | G52: Limited Resources | H52: =IF(I52="",200,VLOOKUP(I52,#REF!,2,FALSE)) -> #REF! | I52: Manage Payment & Wallet | J52: IOS | K52: CNG | L52: /Manage Payment Method & Wallet/CNG/IOS | N52: Ability to simulate API error or offline mode. | O52: Verify graceful handling of Payment Method API failures or network errors. | P52: 1. Trigger API failure scenario. *2. Open Manage payment method. | R52: 1. App receives API error or times out. *2. Screen shows an error message and a retry option or guidance; app does not crash. | S52: It's possible, but not from pure Appium. Therefore, the backend or network must be controlled.
A53: MNDC-T6032 | B53: CNG - MNDC-390 - IOS - Default Payment Method Preselected Green Radio | C53: Jimmy | D53: Done | E53: Passed | F53: Complete | H53: =IF(I53="",200,VLOOKUP(I53,#REF!,2,FALSE)) -> #REF! | I53: Manage Payment & Wallet | J53: IOS | K53: CNG | L53: /Manage Payment Method & Wallet/CNG/IOS | N53: Backend indicates a default method in API response. | O53: Verify the default payment method returned by API is preselected and shows a green radio. | P53: 1. Open Manage payment method. *Move around from one tab or screen to another and validate the above selected payment method is shown on both screens | R53: 1. Screen displays items. *User selected payment methods are shown until a new payment method is saved and selected on both Make a payment and Payment method screens
A54: MNDC-T6029 | B54: CNG - MNDC-390 - IOS - Display Payment Methods List Populated From API | C54: Jimmy | D54: Done | E54: Passed | F54: Complete | H54: =IF(I54="",200,VLOOKUP(I54,#REF!,2,FALSE)) -> #REF! | I54: Manage Payment & Wallet | J54: IOS | K54: CNG | L54: /Manage Payment Method & Wallet/CNG/IOS | N54: User logged in; network available; test account has N stored payment methods (N >= 1); API returns a valid list. | O54: Verify the "Manage payment method" screen displays the payment methods returned by the Payment Method API. | P54: 1. Open Manage payment method screen. *3. Inspect displayed list rows. | R54: 1. App issues Payment Method API request. *3. Screen shows one row per returned method with required labels/masked details and a radio control per row.
A55: MNDC-T6033 | B55: CNG - MNDC-390 - IOS - Save Payment Method Redirect With Loader and New Selection | C55: Kevin | D55: Done | E55: Passed | F55: Complete | H55: =IF(I55="",200,VLOOKUP(I55,#REF!,2,FALSE)) -> #REF! | I55: Manage Payment & Wallet | J55: IOS | K55: CNG | L55: /Manage Payment Method & Wallet/CNG/IOS | N55: Save button visible (remote config ON); network available; backend saves default. | O55: Verify tapping "Save payment method" triggers loader, persists the new selection, and redirects to Make a Payment with that method preselected. | P55: 1. Tap Save payment method. *3. Observe redirection to Make a Payment. | R55: 1. Save flow starts and app calls backend (if applicable). *3. After success, app redirects to Make a Payment and the newly saved method is preselected.
A56: MNDC-T6034 | B56: CNG - MNDC-390 - IOS - Save Without Change no Redirect With Loader | C56: Kevin | D56: Done | E56: Passed | F56: Complete | H56: =IF(I56="",200,VLOOKUP(I56,#REF!,2,FALSE)) -> #REF! | I56: Manage Payment & Wallet | J56: IOS | K56: CNG | L56: /Manage Payment Method & Wallet/CNG/IOS | N56: Save button visible and enabled. | O56: Check that clicking on 'Select Payment Method' without altering any data still shows loader and roll back to Make a Payment without changes in the Payment Method. | P56: Work your way to the Make a Payment screen with an eBill account.
A57: MNDC-T6030 | B57: CNG - MNDC-390 - IOS - Supports payment methods added and are Scrollable | C57: Jimmy | D57: Done | E57: Passed | F57: Complete | H57: =IF(I57="",200,VLOOKUP(I57,#REF!,2,FALSE)) -> #REF! | I57: Manage Payment & Wallet | J57: IOS | K57: CNG | L57: /Manage Payment Method & Wallet/CNG/IOS | N57: Test account prepopulated with added methods; device viewport smaller than list height. | O57: Verify the list supports all the payment methods added and is scrollable so all items can be viewed. | P57: 1. Open Manage payment method. *Validate the icons displayed for ACH and Credit/.Debit card payment methods | R57: 1. List initially shows the top portion of items. *For ACH account and Credit card separate icons are visible
A58: MNDC-T6039 | B58: CNG - MNDC-604 - IOS - Send a message in firebase | C58: Jimmy | D58: No Auto | E58: No Auto | F58: No Auto | G58: For Manual | H58: =IF(I58="",200,VLOOKUP(I58,#REF!,2,FALSE)) -> #REF! | I58: Manage Payment & Wallet | J58: IOS | K58: CNG | L58: /Manage Payment Method & Wallet/CNG/IOS | O58: I need to implement Firebase Cloud Messaging to send over push notifications to customers when is needed | P58: Go to Firebase and setup a message to User | R58: The message should be visible in device
A59: MNDC-T5961 | B59: CNG - MNDC-605 - Android - Send a message in firebase | H59: =IF(I59="",200,VLOOKUP(I59,#REF!,2,FALSE)) -> #REF! | I59: Manage Payment & Wallet | J59: Android | K59: CNG | L59: /Manage Payment Method & Wallet/CNG/Android | O59: I need to implement Firebase Cloud Messaging to send over push notifications to customers when is needed | P59: Go to Firebase and setup a message to User | R59: The message should be visible in device
A60: MNDC-T6022 | B60: CNG - MNDC-613 - IOS - CNG/CNG-group: No Stored payment methods — Add bank account opens Kubra bank-account view | C60: Jimmy | D60: Done | E60: Passed | F60: Complete | H60: =IF(I60="",200,VLOOKUP(I60,#REF!,2,FALSE)) -> #REF! | I60: Manage Payment & Wallet | J60: IOS | K60: CNG | L60: /Manage Payment Method & Wallet/CNG/IOS | N60: - eBill = 'true'. | O60: Validate that Add bank account button redirects to Kubra bank-account onboarding when no stored methods exist. | P60: 1. Click "Add bank account" ,add the proper information and complete the process | R60: User is redirected to Kubra's bank-account onboarding view. Kubra bank account UI (routing number, account number, verification) is displayed. User should see the previous payment method added in list
A61: MNDC-T6021 | B61: CNG - MNDC-613 - IOS - CNG/CNG-group: No stored payment methods — Only "Add bank account" and "Add credit or debit card" visible; Add credit/debit opens Kubra CC/DC view | C61: Jimmy | D61: Done | E61: Passed | F61: Complete | H61: =IF(I61="",200,VLOOKUP(I61,#REF!,2,FALSE)) -> #REF! | I61: Manage Payment & Wallet | J61: IOS | K61: CNG | L61: /Manage Payment Method & Wallet/CNG/IOS | N61: - eBill = 'true'. | O61: Verify when no payment methods are stored for NYSEG-group opcos, user sees only the two Add buttons, and Add credit or debit card opens Kubra CC/DC view. | P61: 1. Confirm no stored payment methods displayed. *3. Click "Add credit or debit card", add the proper information and complete the process | R61: - Only the two Add buttons are shown in UI. *- The Kubra CC/DC view UI elements (card entry fields) are displayed. User should see the previous payment method added in list
A62: MNDC-T6020 | B62: CNG - MNDC-613 - IOS - CNG/CNG-group: Stored payment methods present — "Manage payment methods" redirects to Kubra and shows Payment method screen with all buttons | C62: Jimmy | D62: Done | E62: Passed | F62: Complete | H62: =IF(I62="",200,VLOOKUP(I62,#REF!,2,FALSE)) -> #REF! | I62: Manage Payment & Wallet | J62: IOS | K62: CNG | L62: /Manage Payment Method & Wallet/CNG/IOS | N62: - eBill = 'true'. | O62: Validate that when stored payment methods exist ,"Manage payment methods" redirects to Kubra and the Kubra Payment method screen shows Manage wallet, Add bank account, and Add credit or debit card. | P62: 1. On Make a payment, confirm stored payment methods are listed. *2. Click the "Manage payment methods" control/link. | R62: - Kubra displays the Payment method screen. *- On Kubra Payment method screen, "Manage wallet", "Add bank account", and "Add credit or debit card" buttons are visible and enabled.
A63: MNDC-T6023 | B63: CNG - MNDC-613 - IOS - CNG/UI opcos: Stored payment methods scenario — only "Add bank account" visible; Manage and Add card not shown; Add bank redirects to Kubra bank view | C63: Jimmy | D63: Done | E63: Passed | F63: Complete | H63: =IF(I63="",200,VLOOKUP(I63,#REF!,2,FALSE)) -> #REF! | I63: Manage Payment & Wallet | J63: IOS | K63: CNG | L63: /Manage Payment Method & Wallet/CNG/IOS | N63: - eBill = 'true'. | O63: Ensure CNG and UI opcos only display "Add bank account" (regardless of stored methods) and that it redirects correctly. | P63: 1. Inspect Make a payment UI for Manage payment methods, Add credit or debit card, and Add bank account. *2. Click "Add bank account". | R63: *Only "Add bank account" button is visible; "Manage payment methods" and "Add credit or debit card" are not present. Clicking "Add bank account" redirects to Kubra bank-account view. Kubra bank-account onboarding UI is displayed.
A64: MNDC-T6027 | B64: CNG - MNDC-613 - IOS - Firebase remote config: toggling "Add bank account" button on/off | C64: Jimmy | D64: No Auto | E64: No Auto | F64: No Auto | G64: For Manual | H64: =IF(I64="",200,VLOOKUP(I64,#REF!,2,FALSE)) -> #REF! | I64: Manage Payment & Wallet | J64: IOS | K64: CNG | L64: /Manage Payment Method & Wallet/CNG/IOS | N64: - eBill = 'true'. | O64: Validate Add bank account button visibility follows its remote config key. | P64: 1. Set Add bank account = enabled in Firebase; refresh UI and verify button present. *2. Set Add bank account = disabled; refresh UI and verify button hidden. | R64: - Button appears only when remote config = enabled. *- When disabled, Add bank account is not shown and cannot be used to open Kubra.
A65: MNDC-T6028 | B65: CNG - MNDC-613 - IOS - Firebase remote config: toggling "Add credit and debit credit card" button on/off | C65: Jimmy | D65: No Auto | E65: No Auto | F65: No Auto | G65: For Manual | H65: =IF(I65="",200,VLOOKUP(I65,#REF!,2,FALSE)) -> #REF! | I65: Manage Payment & Wallet | J65: IOS | K65: CNG | L65: /Manage Payment Method & Wallet/CNG/IOS | N65: - eBill = 'true'. | O65: Validate Add credit/debit card button visibility is driven by remote config. | P65: 1. Set Add credit/debit card = enabled; refresh and confirm button visible. *2. Set Add credit/debit card = disabled; refresh and confirm button hidden. | R65: - Button visible only when remote config enabled. *- Hidden when disabled.
A66: MNDC-T6026 | B66: CNG - MNDC-613 - IOS - Firebase remote config: toggling "Manage my wallet" button on/off | C66: Jimmy | D66: No Auto | E66: No Auto | F66: No Auto | G66: For Manual | H66: =IF(I66="",200,VLOOKUP(I66,#REF!,2,FALSE)) -> #REF! | I66: Manage Payment & Wallet | J66: IOS | K66: CNG | L66: /Manage Payment Method & Wallet/CNG/IOS | N66: - eBill = 'true'. | O66: Verify the Manage my wallet button visibility responds to remote config. | P66: 1. Set Manage my wallet remote config = enabled; navigate to Kubra Payment method screen and observe button. *2. Set remote config = disabled; refresh screen. | R66: - When enabled: Manage my wallet button is visible. *- When disabled: Manage my wallet button is not visible.
A67: MNDC-T6025 | B67: CNG - MNDC-613 - IOS - Firebase remote config: toggling "Select payment method" section off hides the section | C67: Jimmy | D67: No Auto | E67: No Auto | F67: No Auto | G67: For Manual | H67: =IF(I67="",200,VLOOKUP(I67,#REF!,2,FALSE)) -> #REF! | I67: Manage Payment & Wallet | J67: IOS | K67: CNG | L67: /Manage Payment Method & Wallet/CNG/IOS | N67: - eBill = 'true'. | O67: Validate Select payment method section visibility follows Firebase remote config key for that section. | P67: 1. Using test Firebase settings, set the remote config key for Select payment method = disabled. *2. Refresh app / reload Make a payment screen. | R67: - Select payment method section is hidden. *- No controls to manage Kubra wallet appear on the Make a payment screen.
A68: MNDC-T6024 | B68: CNG - MNDC-613 - IOS - UI element visibility: "Manage my wallet" button visible (independent test) | C68: Jimmy | D68: Done | E68: Passed | F68: Complete | H68: =IF(I68="",200,VLOOKUP(I68,#REF!,2,FALSE)) -> #REF! | I68: Manage Payment & Wallet | J68: IOS | K68: CNG | L68: /Manage Payment Method & Wallet/CNG/IOS | N68: - eBill = 'true'. | O68: Verify the "Manage my wallet" button is visible in Kubra Payment method screen for opcos that support it and when remote config enables it. | P68: 1. Inspect Kubra Payment method screen for "Manage my wallet" button. | R68: "Manage my wallet" button is visible and enabled. If clicked (optional), it navigates to the wallet management flow (actual navigation validated in integration test).
A69: MNDC-T6019 | B69: CNG - MNDC-613 - IOS - Verify "Select payment method" section is not visible when eBill = 'false' | C69: Jimmy | D69: Done | E69: Passed | F69: Complete | H69: =IF(I69="",200,VLOOKUP(I69,#REF!,2,FALSE)) -> #REF! | I69: Manage Payment & Wallet | J69: IOS | K69: CNG | L69: /Manage Payment Method & Wallet/CNG/IOS | N69: - Customer account with eBill = 'false'. | O69: Ensure the Select payment method section is hidden for customers with eBill flag = 'false'. | P69: 1. Navigate to Make a payment. | R69: - No links or buttons that open Kubra for payment-method management are visible.
A70: MNDC-T6018 | B70: CNG - MNDC-613 - IOS - Verify "Select payment method" section is visible when eBill = 'true' | C70: Jimmy | D70: Done | E70: Passed | F70: Complete | H70: =IF(I70="",200,VLOOKUP(I70,#REF!,2,FALSE)) -> #REF! | I70: Manage Payment & Wallet | J70: IOS | K70: CNG | L70: /Manage Payment Method & Wallet/CNG/IOS | N70: - eBill flag set to 'true' on the customer profile. | O70: Ensure the payment management entry point (Select payment method section) is visible only for customers with eBill flag = 'true'. | P70: 1. Navigate to Make a payment. | R70: - The Select payment method section (or payment-method entry point) is displayed.
A71: MNDC-T5944 | B71: CNG - MNDC-614 - Android - CNG/SCG-group: No Stored payment methods — Add bank account opens Kubra bank-account view | C71: Jimmy | D71: Done | E71: Passed | F71: Done | H71: =IF(I71="",200,VLOOKUP(I71,#REF!,2,FALSE)) -> #REF! | I71: Manage Payment & Wallet | J71: Android | K71: CNG | L71: /Manage Payment Method & Wallet/CNG/Android | N71: - eBill = 'true'. | O71: Validate that Add bank account button redirects to Kubra bank-account onboarding when no stored methods exist. | P71: 1. Click "Add bank account". | R71: User is redirected to Kubra's bank-account onboarding view. Kubra bank account UI (routing number, account number, verification) is displayed.
A72: MNDC-T5943 | B72: CNG - MNDC-614 - Android - CNG/SCG-group: No stored payment methods — Only "Add bank account" and "Add credit or debit card" visible; Add credit/debit opens Kubra CC/DC view | C72: Jimmy | D72: Done | E72: Passed | F72: Done | H72: =IF(I72="",200,VLOOKUP(I72,#REF!,2,FALSE)) -> #REF! | I72: Manage Payment & Wallet | J72: Android | K72: CNG | L72: /Manage Payment Method & Wallet/CNG/Android | N72: - eBill = 'true'. | O72: Verify when no payment methods are stored for NYSEG-group opcos, user sees only the two Add buttons, and Add credit or debit card opens Kubra CC/DC view. | P72: 1. Confirm no stored payment methods displayed. *3. Click "Add credit or debit card". | R72: - Only the two Add buttons are shown in UI. *- The Kubra CC/DC view UI elements (card entry fields) are displayed.
A73: MNDC-T5942 | B73: CNG - MNDC-614 - Android - CNG/SCG-group: Stored payment methods present — "Manage payment methods" redirects to Kubra and shows Payment method screen with all buttons | C73: Jimmy | D73: Done | E73: Passed | F73: Done | H73: =IF(I73="",200,VLOOKUP(I73,#REF!,2,FALSE)) -> #REF! | I73: Manage Payment & Wallet | J73: Android | K73: CNG | L73: /Manage Payment Method & Wallet/CNG/Android | N73: - eBill = 'true'. | O73: Validate that when stored payment methods exist ,"Manage payment methods" redirects to Kubra and the Kubra Payment method screen shows Manage wallet, Add bank account, and Add credit or debit card. | P73: 1. On Make a payment, confirm stored payment methods are listed. *2. Click the "Manage payment methods" control/link. | R73: - Kubra displays the Payment method screen. *- On Kubra Payment method screen, "Manage wallet", "Add bank account", and "Add credit or debit card" buttons are visible and enabled.
A74: MNDC-T5945 | B74: CNG - MNDC-614 - Android - CNG/UI opcos: Stored payment methods scenario — only "Add bank account" visible; Manage and Add card not shown; Add bank redirects to Kubra bank view | C74: Jimmy | D74: Done | E74: Passed | F74: Done | H74: =IF(I74="",200,VLOOKUP(I74,#REF!,2,FALSE)) -> #REF! | I74: Manage Payment & Wallet | J74: Android | K74: CNG | L74: /Manage Payment Method & Wallet/CNG/Android | N74: - eBill = 'true'. | O74: Ensure CNG and UI opcos only display "Add bank account" (regardless of stored methods) and that it redirects correctly. | P74: 1. Inspect Make a payment UI for Manage payment methods, Add credit or debit card, and Add bank account. *2. Click "Add bank account". | R74: *Only "Add bank account" button is visible; "Manage payment methods" and "Add credit or debit card" are not present. Clicking "Add bank account" redirects to Kubra bank-account view. Kubra bank-account onboarding UI is displayed.
A75: MNDC-T5949 | B75: CNG - MNDC-614 - Android - Firebase remote config: toggling "Add bank account" button on/off | H75: =IF(I75="",200,VLOOKUP(I75,#REF!,2,FALSE)) -> #REF! | I75: Manage Payment & Wallet | J75: Android | K75: CNG | L75: /Manage Payment Method & Wallet/CNG/Android | N75: - eBill = 'true'. | O75: Validate Add bank account button visibility follows its remote config key. | P75: 1. Set Add bank account = enabled in Firebase; refresh UI and verify button present. *2. Set Add bank account = disabled; refresh UI and verify button hidden. | R75: - Button appears only when remote config = enabled. *- When disabled, Add bank account is not shown and cannot be used to open Kubra.
A76: MNDC-T5950 | B76: CNG - MNDC-614 - Android - Firebase remote config: toggling "Add credit and debit credit card" button on/off | H76: =IF(I76="",200,VLOOKUP(I76,#REF!,2,FALSE)) -> #REF! | I76: Manage Payment & Wallet | J76: Android | K76: CNG | L76: /Manage Payment Method & Wallet/CNG/Android | N76: - eBill = 'true'. | O76: Validate Add credit/debit card button visibility is driven by remote config. | P76: 1. Set Add credit/debit card = enabled; refresh and confirm button visible. *2. Set Add credit/debit card = disabled; refresh and confirm button hidden. | R76: - Button visible only when remote config enabled. *- Hidden when disabled.
A77: MNDC-T5948 | B77: CNG - MNDC-614 - Android - Firebase remote config: toggling "Manage my wallet" button on/off | H77: =IF(I77="",200,VLOOKUP(I77,#REF!,2,FALSE)) -> #REF! | I77: Manage Payment & Wallet | J77: Android | K77: CNG | L77: /Manage Payment Method & Wallet/CNG/Android | N77: - eBill = 'true'. | O77: Verify the Manage my wallet button visibility responds to remote config. | P77: 1. Set Manage my wallet remote config = enabled; navigate to Kubra Payment method screen and observe button. *2. Set remote config = disabled; refresh screen. | R77: - When enabled: Manage my wallet button is visible. *- When disabled: Manage my wallet button is not visible.
A78: MNDC-T5947 | B78: CNG - MNDC-614 - Android - Firebase remote config: toggling "Select payment method" section off hides the section | H78: =IF(I78="",200,VLOOKUP(I78,#REF!,2,FALSE)) -> #REF! | I78: Manage Payment & Wallet | J78: Android | K78: CNG | L78: /Manage Payment Method & Wallet/CNG/Android | N78: - eBill = 'true'. | O78: Validate Select payment method section visibility follows Firebase remote config key for that section. | P78: 1. Using test Firebase settings, set the remote config key for Select payment method = disabled. *2. Refresh app / reload Make a payment screen. | R78: - Select payment method section is hidden. *- No controls to manage Kubra wallet appear on the Make a payment screen.
A79: MNDC-T5946 | B79: CNG - MNDC-614 - Android - UI element visibility: "Manage my wallet" button visible (independent test) | C79: Jimmy | D79: Done | E79: Passed | F79: Done | H79: =IF(I79="",200,VLOOKUP(I79,#REF!,2,FALSE)) -> #REF! | I79: Manage Payment & Wallet | J79: Android | K79: CNG | L79: /Manage Payment Method & Wallet/CNG/Android | N79: - eBill = 'true'. | O79: Verify the "Manage my wallet" button is visible in Kubra Payment method screen for opcos that support it and when remote config enables it. | P79: 1. Inspect Kubra Payment method screen for "Manage my wallet" button. | R79: "Manage my wallet" button is visible and enabled. If clicked (optional), it navigates to the wallet management flow (actual navigation validated in integration test).
A80: MNDC-T5941 | B80: CNG - MNDC-614 - Android - Verify "Select payment method" section is not visible when eBill = 'false' | C80: Jimmy | D80: Done | E80: Passed | F80: Done | H80: =IF(I80="",200,VLOOKUP(I80,#REF!,2,FALSE)) -> #REF! | I80: Manage Payment & Wallet | J80: Android | K80: CNG | L80: /Manage Payment Method & Wallet/CNG/Android | N80: - Customer account with eBill = 'false'. | O80: Ensure the Select payment method section is hidden for customers with eBill flag = 'false'. | P80: 1. Navigate to Make a payment. | R80: - No links or buttons that open Kubra for payment-method management are visible.
A81: MNDC-T5940 | B81: CNG - MNDC-614 - Android - Verify "Select payment method" section is visible when eBill = 'true' | C81: Jimmy | D81: Done | E81: Passed | F81: Done | H81: =IF(I81="",200,VLOOKUP(I81,#REF!,2,FALSE)) -> #REF! | I81: Manage Payment & Wallet | J81: Android | K81: CNG | L81: /Manage Payment Method & Wallet/CNG/Android | N81: - eBill flag set to 'true' on the customer profile. | O81: Ensure the payment management entry point (Select payment method section) is visible only for customers with eBill flag = 'true'. | P81: 1. Navigate to Make a payment. | R81: - The Select payment method section (or payment-method entry point) is displayed.
A82: MNDC-T6016 | B82: CNG - MNDC-621 - IOS - Backend deletion API call is triggered and succeeds | C82: Jimmy | D82: Blocked | E82: Blocked | F82: For Future | H82: =IF(I82="",200,VLOOKUP(I82,#REF!,2,FALSE)) -> #REF! | I82: Manage Payment & Wallet | J82: IOS | K82: CNG | L82: /Manage Payment Method & Wallet/CNG/IOS | O82: Validate that a backend delete API call is made and returns success when deleting a method. | P82: 1. Swipe right to reveal bin icon. *3. Inspect captured network requests. | R82: *- UI is updated to remove the method after success.
A83: MNDC-T6017 | B83: CNG - MNDC-621 - IOS - Delete a payment hidden when eBill flag is false | C83: Jimmy | D83: Done | E83: Passed | F83: Complete | H83: =IF(I83="",200,VLOOKUP(I83,#REF!,2,FALSE)) -> #REF! | I83: Manage Payment & Wallet | J83: IOS | K83: CNG | L83: /Manage Payment Method & Wallet/CNG/IOS | N83: Payment method screen available. | O83: Verify the delete-by-swipe feature is not visible if eBill != 'true'. | P83: 1. Log in with test user. *3. Attempt to swipe a row to the right. | R83: *- If the entire feature must be hidden by flag, the "delete" affordance should not exist.
A84: MNDC-T6014 | B84: CNG - MNDC-621 - IOS - Delete bin icon appears after swipe right | C84: Jimmy | D84: Done | E84: Passed | F84: Complete | H84: =IF(I84="",200,VLOOKUP(I84,#REF!,2,FALSE)) -> #REF! | I84: Manage Payment & Wallet | J84: IOS | K84: CNG | L84: /Manage Payment Method & Wallet/CNG/IOS | N84: - User has eBill = 'true' and cashOnly = 'true' and kubra-managed wallet. At least one stored payment method present. | O84: Verify that swiping a payment method row to the right displays a red bin icon that is clickable. | P84: 1. On "Payment Method" screen, perform a right-swipe gesture on a payment method row. | R84: A red bin (delete) icon is revealed on that row. The bin icon should be enabled (clickable/tappable). Test passes if the bin icon is visible, red, and enabled.
A85: MNDC-T6015 | B85: CNG - MNDC-621 - IOS - Perform deletion by tapping bin icon (no Kubra wallet entry) | C85: Jimmy | D85: Done | E85: Passed | F85: Complete | H85: =IF(I85="",200,VLOOKUP(I85,#REF!,2,FALSE)) -> #REF! | I85: Manage Payment & Wallet | J85: IOS | K85: CNG | L85: /Manage Payment Method & Wallet/CNG/IOS | N85: Flags and kubra-managed wallet set as required. A payment method exists. Network capture or logs available to verify no Kubra redirect; instrumentation to detect navigation to external Kubra flow. | O85: Verify tapping the bin icon deletes the payment method and does not open Kubra wallet. | P85: 1. Swipe right to reveal the bin icon. *2. Tap the bin icon. | R85: *The app initiates deletion locally and/or via app backend API. The app must NOT navigate to or require entry into Kubra wallet UI. The payment method disappears from the list once deletion succeeds. If a confirmation dialog is part of the product (not in requirement), verify the dialog appears and after confirming the deletion proceeds; if no confirmation exists, the deletion should happen immediately. Test passes if the method is removed and there is no Kubra wallet navigation.
A86: MNDC-T5938 | B86: CNG - MNDC-624 - Android - Backend deletion API call is triggered and succeeds | C86: Jimmy | D86: Blocked | E86: Blocked | F86: For Future | H86: =IF(I86="",200,VLOOKUP(I86,#REF!,2,FALSE)) -> #REF! | I86: Manage Payment & Wallet | J86: Android | K86: CNG | L86: /Manage Payment Method & Wallet/CNG/Android | O86: Validate that a backend delete API call is made and returns success when deleting a method. | P86: 1. Swipe right to reveal bin icon. *3. Inspect captured network requests. | R86: *- UI is updated to remove the method after success.
A87: MNDC-T5939 | B87: CNG - MNDC-624 - Android - Delete a payment hidden when eBill flag is false | C87: Jimmy | D87: Done | E87: Passed | F87: Done | H87: =IF(I87="",200,VLOOKUP(I87,#REF!,2,FALSE)) -> #REF! | I87: Manage Payment & Wallet | J87: Android | K87: CNG | L87: /Manage Payment Method & Wallet/CNG/Android | N87: Payment method screen available. | O87: Verify the delete-by-swipe feature is not visible if eBill != 'true'. | P87: 1. Log in with test user. *3. Attempt to swipe a row to the right. | R87: *- If the entire feature must be hidden by flag, the "delete" affordance should not exist.
A88: MNDC-T5936 | B88: CNG - MNDC-624 - Android - Delete bin icon appears after swipe right | C88: Jimmy | D88: Done | E88: Passed | F88: Done | H88: =IF(I88="",200,VLOOKUP(I88,#REF!,2,FALSE)) -> #REF! | I88: Manage Payment & Wallet | J88: Android | K88: CNG | L88: /Manage Payment Method & Wallet/CNG/Android | N88: - User has eBill = 'true' and cashOnly = 'true' and kubra-managed wallet. At least one stored payment method present. | O88: Verify that swiping a payment method row to the right displays a red bin icon that is clickable. | P88: 1. On "Payment Method" screen, perform a right-swipe gesture on a payment method row. | R88: A red bin (delete) icon is revealed on that row. The bin icon should be enabled (clickable/tappable). Test passes if the bin icon is visible, red, and enabled.
A89: MNDC-T5937 | B89: CNG - MNDC-624 - Android - Perform deletion by tapping bin icon (no Kubra wallet entry) | C89: Jimmy | D89: Done | E89: Passed | F89: Done | H89: =IF(I89="",200,VLOOKUP(I89,#REF!,2,FALSE)) -> #REF! | I89: Manage Payment & Wallet | J89: Android | K89: CNG | L89: /Manage Payment Method & Wallet/CNG/Android | N89: Flags and kubra-managed wallet set as required. A payment method exists. Network capture or logs available to verify no Kubra redirect; instrumentation to detect navigation to external Kubra flow. | O89: Verify tapping the bin icon deletes the payment method and does not open Kubra wallet. | P89: 1. Swipe right to reveal the bin icon. *2. Tap the bin icon. | R89: *The app initiates deletion locally and/or via app backend API. The app must NOT navigate to or require entry into Kubra wallet UI. The payment method disappears from the list once deletion succeeds. If a confirmation dialog is part of the product (not in requirement), verify the dialog appears and after confirming the deletion proceeds; if no confirmation exists, the deletion should happen immediately. Test passes if the method is removed and there is no Kubra wallet navigation.
A90: MNDC-T7041 | B90: - CNG - MNDC-265 - IOS - Successful Payment Processed via Apple Pay (End-to-End) (cloned) | H90: =IF(I90="",200,VLOOKUP(I90,#REF!,2,FALSE)) -> #REF! | I90: Make a Payment Flow | J90: IOS | K90: CNG | L90: /Make a Payment-IOS-CNG-SCG-Realdevice-Regression/Applepay-CNG-SCG-Realdevice | N90: - User logged in; Today's Date selected; outstanding balance visible; payment amount selected. | O90: - Objective: Validate full successful payment flow through Apple Pay with confirmation screen shown containing transaction details. | P90: 1. Select Apple Pay and tap confirm. *3. Wait for payment processing. | R90: 1. Authentication succeeds. *3. Confirmation screen displays transaction ID/reference. Test passes if payment completes and confirmation screen shows correct details.
A91: MNDC-T5260 | B91: CNG - Android - MNDC-282 - Custom Value not showing for Final Notice | H91: =IF(I91="",200,VLOOKUP(I91,#REF!,2,FALSE)) -> #REF! | I91: Make a Payment Flow | J91: Android | K91: CNG | L91: /Make a Payment Flow/CNG/Android | M91: MNDC-1065 | O91: Custom Value not showing for Final Notice | P91: Open an account that has a due payable ammount on Final Notice status, and flow to the payment screen; *Select to pay the bill (via the payment widget or Bills tab) and check that the payment doesn't show the option of Custom Ammount.
A92: MNDC-T5261 | B92: CNG - Android - MNDC-282 - Custom Value not showing for Past Due | H92: =IF(I92="",200,VLOOKUP(I92,#REF!,2,FALSE)) -> #REF! | I92: Make a Payment Flow | J92: Android | K92: CNG | L92: /Make a Payment Flow/CNG/Android | M92: MNDC-1065 | O92: Custom Value not showing for Past Due | P92: Open an account that has a due payable ammount on Past Due status, and flow to the payment screen; *Select to pay the bill (via the payment widget or Bills tab) and check that the payment doesn't show the option of Custom Ammount.
A93: MNDC-T5259 | B93: CNG - Android - MNDC-282 - Custom Value selection | H93: =IF(I93="",200,VLOOKUP(I93,#REF!,2,FALSE)) -> #REF! | I93: Make a Payment Flow | J93: Android | K93: CNG | L93: /Make a Payment Flow/CNG/Android | O93: Custom Value selection | P93: Open an account that has a due payable ammount, and flow to the payment screen; *The app should mark the Custom Value as the selected choice.
A94: MNDC-T5258 | B94: CNG - Android - MNDC-282 - Keyboard not overlapping and retractability | H94: =IF(I94="",200,VLOOKUP(I94,#REF!,2,FALSE)) -> #REF! | I94: Make a Payment Flow | J94: Android | K94: CNG | L94: /Make a Payment Flow/CNG/Android | O94: Keyboard not overlapping and retractability | P94: Open an account that has a due payable ammount, and flow to the payment screen; *Click outside the keyboard and check that it should be retracted.
A95: MNDC-T5257 | B95: CNG - Android - MNDC-282 - Keyboard visibility and retractability | H95: =IF(I95="",200,VLOOKUP(I95,#REF!,2,FALSE)) -> #REF! | I95: Make a Payment Flow | J95: Android | K95: CNG | L95: /Make a Payment Flow/CNG/Android | O95: Keyboard visibility and retractability | P95: Open an account that has a due payable ammount, and flow to the payment screen; *After selecting the ammount, click on Done and check that the keyboard are retracted.
A96: MNDC-T5262 | B96: CNG - Android - MNDC-282 - Payment confirmation screen and payment confirmation | H96: =IF(I96="",200,VLOOKUP(I96,#REF!,2,FALSE)) -> #REF! | I96: Make a Payment Flow | J96: Android | K96: CNG | L96: /Make a Payment Flow/CNG/Android | M96: MNDC-1065 | O96: Payment confirmation screen and payment confirmation | P96: Open an account that has a due payable ammount, and flow to the payment screen; *Select to go though and validate that there is a payment confirmation screen as well.
A97: MNDC-T5263 | B97: CNG - Android - MNDC-282 - Remote Config enable and disable | H97: =IF(I97="",200,VLOOKUP(I97,#REF!,2,FALSE)) -> #REF! | I97: Make a Payment Flow | J97: Android | K97: CNG | L97: /Make a Payment Flow/CNG/Android | M97: MNDC-1065 | O97: Remote Config enable and disable | P97: Select enable on the Remote Config for the following items: Amount Due, Total Balance and 'Custom Amount' header and the field itself; *Open your session one last time and check that the fields are showing and also operational.
A98: MNDC-T5256 | B98: CNG - Android - MNDC-282 - Validate the accordion's fields: Payment Agreement | H98: =IF(I98="",200,VLOOKUP(I98,#REF!,2,FALSE)) -> #REF! | I98: Make a Payment Flow | J98: Android | K98: CNG | L98: /Make a Payment Flow/CNG/Android | M98: MNDC-1065 | O98: Validate the accordion's fields: Payment Agreement | P98: Open an account that has a due payable ammount with a Payable Agreement, and flow to the payment screen; *Select to pay the bill (via the payment widget or Bills tab) and check that the accordion is available and shows the fields: Amount Due, Total Balance
A99: MNDC-T5255 | B99: CNG - Android - MNDC-282 - Validate the accordion's fields: W/O Payment Agreement | H99: =IF(I99="",200,VLOOKUP(I99,#REF!,2,FALSE)) -> #REF! | I99: Make a Payment Flow | J99: Android | K99: CNG | L99: /Make a Payment Flow/CNG/Android | M99: MNDC-1065 | O99: Validate the accordion's fields: W/O Payment Agreement | P99: Open an account that has a due payable ammount without a Payment Agreement, and flow to the payment screen; *Select to pay the bill (via the payment widget or Bills tab) and check that the accordion is available and shows the fields: Amount Due and Custom Amount.
A100: MNDC-T5242 | B100: CNG - Android - MNDC-282 - Validate the default ammount displayed | H100: =IF(I100="",200,VLOOKUP(I100,#REF!,2,FALSE)) -> #REF! | I100: Make a Payment Flow | J100: Android | K100: CNG | L100: /Make a Payment Flow/CNG/Android | O100: Validate the default ammount displayed | P100: Open an account that has a due payable ammount, and flow to the payment screen; *Select to pay the bill (via the payment widget or Bills tab) and check that the payment amount default is the amount due.
...

Sheet Data
A1: Assigned to | B1: Scripts | C1: Tests | D1: Status
A2: Jimmy | B2: In Progress | C2: In Progress | D2: In Progress
A3: Kevin | B3: Failed | C3: Failed | D3: For Future
A4: Erick | B4: Blocked | C4: Blocked | D4: For Manual
A5: Surekha | B5: Done | C5: Passed | D5: Limited Resources
B6: No Auto | C6: No Auto | D6: Unstable
D7: Blocked
D8: Complete
D9: No Auto

Sheet MASTER PLAN_OLD
C1: March | Z1: April | BD1: May | CI1: June | DM1: July
C2: M | D2: T | E2: W | F2: Th | G2: F | H2: SA | I2: SU | J2: M | K2: T | L2: W | M2: Th | N2: F | O2: SA | P2: SU | Q2: M | R2: T | S2: W | T2: Th | U2: F | V2: SA | W2: SU | X2: M | Y2: T | Z2: W | AA2: Th | AB2: F | AC2: SA | AD2: SU | AE2: M | AF2: T | AG2: W | AH2: Th | AI2: F | AJ2: SA | AK2: SU | AL2: M | AM2: T | AN2: W | AO2: Th | AP2: F | AQ2: SA | AR2: SU | AS2: M | AT2: T | AU2: W | AV2: Th | AW2: F | AX2: SA | AY2: SU | AZ2: M | BA2: T | BB2: W | BC2: Th | BD2: F | BE2: SA | BF2: SU | BG2: M | BH2: T | BI2: W | BJ2: Th | BK2: F | BL2: SA | BM2: SU | BN2: M | BO2: T | BP2: W | BQ2: Th | BR2: F | BS2: SA | BT2: SU | BU2: M | BV2: T | BW2: W | BX2: Th | BY2: F | BZ2: SA | CA2: SU | CB2: M | CC2: T | CD2: W | CE2: Th | CF2: F | CG2: SA | CH2: SU | CI2: M | CJ2: T | CK2: W | CL2: Th | CM2: F | CN2: SA | CO2: SU | CP2: M | CQ2: T | CR2: W | CS2: Th | CT2: F | CU2: SA | CV2: SU | CW2: M | CX2: T | CY2: W | CZ2: Th | DA2: F | DB2: SA | DC2: SU | DD2: M | DE2: T | DF2: W | DG2: Th | DH2: F | DI2: SA | DJ2: SU | DK2: M | DL2: T | DM2: W | DN2: Th | DO2: F | DP2: SA | DQ2: SU | DR2: M | DS2: T | DT2: W | DU2: Th | DV2: F | DW2: SA | DX2: SU
C3: 9 | D3: 10 | E3: 11 | F3: 12 | G3: 13 | H3: 14 | I3: 15 | J3: 16 | K3: 17 | L3: 18 | M3: 19 | N3: 20 | O3: 21 | P3: 22 | Q3: 23 | R3: 24 | S3: 25 | T3: 26 | U3: 27 | V3: 28 | W3: 29 | X3: 30 | Y3: 31 | Z3: 1 | AA3: 2 | AB3: 3 | AC3: 4 | AD3: 5 | AE3: 6 | AF3: 7 | AG3: 8 | AH3: 9 | AI3: 10 | AJ3: 11 | AK3: 12 | AL3: 13 | AM3: 14 | AN3: 15 | AO3: 16 | AP3: 17 | AQ3: 18 | AR3: 19 | AS3: 20 | AT3: 21 | AU3: 22 | AV3: 23 | AW3: 24 | AX3: 25 | AY3: 26 | AZ3: 27 | BA3: 28 | BB3: 29 | BC3: 30 | BD3: 1 | BE3: 2 | BF3: 3 | BG3: 4 | BH3: 5 | BI3: 6 | BJ3: 7 | BK3: 8 | BL3: 9 | BM3: 10 | BN3: 11 | BO3: 12 | BP3: 13 | BQ3: 14 | BR3: 15 | BS3: 16 | BT3: 17 | BU3: 18 | BV3: 19 | BW3: 20 | BX3: 21 | BY3: 22 | BZ3: 23 | CA3: 24 | CB3: 25 | CC3: 26 | CD3: 27 | CE3: 28 | CF3: 29 | CG3: 30 | CH3: 31 | CI3: 1 | CJ3: 2 | CK3: 3 | CL3: 4 | CM3: 5 | CN3: 6 | CO3: 7 | CP3: 8 | CQ3: 9 | CR3: 10 | CS3: 11 | CT3: 12 | CU3: 13 | CV3: 14 | CW3: 15 | CX3: 16 | CY3: 17 | CZ3: 18 | DA3: 19 | DB3: 20 | DC3: 21 | DD3: 22 | DE3: 23 | DF3: 24 | DG3: 25 | DH3: 26 | DI3: 27 | DJ3: 28 | DK3: 29 | DL3: 30 | DM3: 1 | DN3: 2 | DO3: 3 | DP3: 4 | DQ3: 5 | DR3: 6 | DS3: 7 | DT3: 8 | DU3: 9 | DV3: 10 | DW3: 11 | DX3: 12
B4: BGC - iOS / Android
B5: CMP - iOS / Android | L5: QAT | Z5: Regression
B6: NYSEG - iOS / Android | AN6: QAT | BB6: Regression
B7: RG&E - iOS / Android | BP7: QAT | CD7: Regression
B8: UI - iOS / Android | CR8: QAT | DF8: Regression
A9: Automation Cycles | B9: Status
A10: Regression | B10: In Progress
A11: Manage Payment & Wallet | B11: In Progress
A12: CNG - iOS | B12: QA Validation
A13: CNG - Android | B13: QA Validation
A14: SCG - iOS | B14: Backlog
A15: SCG - Android | B15: Backlog
A16: BCG - iOS | B16: Backlog
A17: BCG - Android | B17: Backlog
A18: CMP - iOS | B18: Backlog
A19: CMP - Android | B19: Backlog
A20: NYSEG - iOS | B20: Backlog
... A206: UI - Android | B206: Backlog

Sheet MASTER PLAN
C1: Past | D1: 46090 | E1: =D1+7 -> 46097 | F1: =E1+7 -> 46104 | G1: =F1+7 -> 46111 | H1: =G1+7 -> 46118 | I1: =H1+7 -> 46125 | J1: =I1+7 -> 46132 | K1: =J1+7 -> 46139 | L1: =K1+7 -> 46146 | ... U1: =T1+7 -> 46209
A2: BGC - iOS / Android | B2: BGC - iOS / Android | X2: Release
A3: CMP - iOS / Android | B3: CMP - iOS / Android | X3: QAT
A4: NYSEG - iOS / Android | B4: NYSEG - iOS / Android | X4: Regression
A5: RG&E - iOS / Android | B5: RG&E - iOS / Android | X5: Mobile Automation
A6: UI - iOS / Android | B6: UI - iOS / Android | X6: Regression Milestone (target for OPCO mobile completion)
A7: Automation Cycles | B7: Status
A8: Regression | B8: In Progress
A9: Manage Payment & Wallet | B9: In Progress
A10: CNG - iOS/Android | B10: QA Validation
A11: SCG - iOS/Android | B11: Backlog
A12: BCG - iOS/Android | B12: Backlog
A13: CMP - iOS/Android | B13: Backlog
A14: NYSEG - iOS/Android | B14: Backlog
A15: RGE - iOS/Android | B15: Backlog
A16: UI - iOS/Android | B16: Backlog
A17: Make a Payment Flow | B17: In Progress
A18: CNG - iOS/Android | B18: In Progress
... A113: UI - iOS/Android | B113: Backlog

Sheet MASTER PLAN (4)
C1: Past | D1: 46090 | E1: =D1+7 -> 46097 | F1: =E1+7 -> 46104 | G1: =F1+7 -> 46111 | H1: =G1+7 -> 46118 | I1: =H1+7 -> 46125 | J1: =I1+7 -> 46132 | K1: =J1+7 -> 46139 | L1: =K1+7 -> 46146 | ... U1: =T1+7 -> 46209
A2: BGC - iOS / Android | B2: BGC - iOS / Android
A3: CMP - iOS / Android | B3: CMP - iOS / Android
A4: NYSEG - iOS / Android | B4: NYSEG - iOS / Android
A5: RG&E - iOS / Android | B5: RG&E - iOS / Android
A6: UI - iOS / Android | B6: UI - iOS / Android
A7: Automation Cycles | B7: Status
A8: CNG - iOS/Android | B8: In Progress
A9: Manage Payment & Wallet | B9: QA Validation
A10: Make a Payment Flow | B10: Backlog
A11: Log In | B11: Backlog
A12: Widget | B12: Backlog
A13: Bills & Payment | B13: Backlog
A14: My Preferences | B14: Backlog
A15: Dahsboard
A16: My Accounts
A17: Outages
A18: Safety
A19: Promo
A20: Liferay
A21: Surveys
A22: SCG - iOS/Android | B22: In Progress
A23: Manage Payment & Wallet | B23: QA Validation
A24: Make a Payment Flow | B24: Backlog
A25: Log In | B25: Backlog
A26: Widget | B26: Backlog
A27: Bills & Payment | B27: Backlog
A28: My Preferences | B28: Backlog
A29: Dahsboard
A30: My Accounts
A31: Outages
A32: Safety
A33: Promo
A34: Liferay
A35: Surveys
A36: BCG - iOS/Android | B36: Backlog
A37: Manage Payment & Wallet | B37: QA Validation
A38: Make a Payment Flow | B38: Backlog
A39: Log In | B39: Backlog
A40: Widget | B40: Backlog
A41: Bills & Payment | B41: Backlog
A42: My Preferences | B42: Backlog
A43: Dahsboard
A44: My Accounts
A45: Outages
A46: Safety
A47: Promo
A48: Liferay
A49: Surveys
A50: CMP - iOS/Android | B50: Backlog
A51: Manage Payment & Wallet | B51: QA Validation
A52: Make a Payment Flow | B52: Backlog
A53: Log In | B53: Backlog
A54: Widget | B54: Backlog
A55: Bills & Payment | B55: Backlog
A56: My Preferences | B56: Backlog
A57: Dahsboard
A58: My Accounts
A59: Outages
A60: Safety
A61: Promo
A62: Liferay
A63: Surveys
A64: NYSEG - iOS/Android | B64: Backlog
A65: Manage Payment & Wallet | B65: QA Validation
A66: Make a Payment Flow | B66: Backlog
A67: Log In | B67: Backlog
A68: Widget | B68: Backlog
A69: Bills & Payment | B69: Backlog
A70: My Preferences | B70: Backlog
A71: Dahsboard
A72: My Accounts
A73: Outages
A74: Safety
A75: Promo
A76: Liferay
A77: Surveys
A78: RGE - iOS/Android | B78: Backlog
A79: Manage Payment & Wallet | B79: QA Validation
A80: Make a Payment Flow | B80: Backlog
A81: Log In | B81: Backlog
A82: Widget | B82: Backlog
A83: Bills & Payment | B83: Backlog
A84: My Preferences | B84: Backlog
A85: Dahsboard
A86: My Accounts
A87: Outages
A88: Safety
A89: Promo
A90: Liferay
A91: Surveys
A92: UI - iOS/Android | B92: Backlog
A93: Manage Payment & Wallet | B93: QA Validation
A94: Make a Payment Flow | B94: Backlog
A95: Log In | B95: Backlog
A96: Widget | B96: Backlog
A97: Bills & Payment | B97: Backlog
A98: My Preferences | B98: Backlog
A99: Dahsboard
A100: My Accounts
...

Sheet Regression View
B1: Past | C1: 46090 | D1: =C1+7 -> 46097 | E1: =D1+7 -> 46104 | F1: =E1+7 -> 46111 | G1: =F1+7 -> 46118 | H1: =G1+7 -> 46125 | I1: =H1+7 -> 46132 | J1: =I1+7 -> 46139 | K1: =J1+7 -> 46146 | ... T1: =S1+7 -> 46209
A2: BGC - iOS / Android | W2: Release
A3: CMP - iOS / Android | W3: QAT
A4: NYSEG - iOS / Android | W4: Regression
A5: RG&E - iOS / Android | W5: Mobile Automation
A6: UI - iOS / Android | W6: Regression Milestone (target for OPCO mobile completion)
A7: Automation Cycles
A8: Regression
A9: Manage Payment & Wallet
A10: CNG - iOS/Android
A11: SCG - iOS/Android
A12: BCG - iOS/Android
A13: CMP - iOS/Android
A14: NYSEG - iOS/Android
A15: RGE - iOS/Android
A16: UI - iOS/Android
A17: Make a Payment Flow
A18: CNG - iOS/Android
... A24: UI - iOS/Android

Sheet Exec View
H2: Status
B3: OPCO | C3: Module | D3: Platform | E3: Total TC | F3: No Auto | G3: Automated TCs | H3: Pending | I3: In Progress | J3: QA Validation | K3: Auto
B4: CMP | C4: Manage Payments & Methods | D4: Android | E4: =COUNTA(ManagePayments!B7:B30) -> 24 | F4: =COUNTIF(ManagePayments!D7:D30,"No Auto") -> 7 | G4: =COUNTIFS(ManagePayments!D7:D30,"<>No Auto",ManagePayments!D7:D30,"<>") -> 17 | H4: =COUNTIF(ManagePayments!$D$7:$D$30,"=In Progress") -> 0 | I4: =COUNTIF(ManagePayments!$D$7:$D$30,"=In Progress") -> 0 | J4: =COUNTIF(ManagePayments!$D$7:$D$30,"=QA Validation") -> 17
D5: iOS | E5: =COUNTA(ManagePayments!B32:B55) -> 24 | F5: =COUNTIF(ManagePayments!D32:D55,"No Auto") -> 4 | G5: =COUNTIFS(ManagePayments!D32:D55,"<>No Auto",ManagePayments!D32:D55,"<>") -> 20 | H5: =COUNTIF(ManagePayments!$D$32:$D$55,"=In Progress") -> 0 | I5: =COUNTIF(ManagePayments!$D$32:$D$55,"=In Progress") -> 0 | J5: =COUNTIF(ManagePayments!$D$32:$D$55,"=QA Validation") -> 20
C6: Make a Payment Flow | D6: Android | E6: =COUNTA(MakePayment!B7:B57) -> 51 | F6: =COUNTIF(MakePayment!D7:D57,"No Auto") -> 4 | G6: =COUNTIFS(MakePayment!D7:D57,"<>No Auto",MakePayment!D7:D57,"<>") -> 0 | H6: 47 | I6: =COUNTIF(MakePayment!$D$7:$D$57,"=In Progress") -> 0 | J6: =COUNTIF(MakePayment!$D$7:$D$57,"=QA Validation") -> 0
D7: iOS | E7: =COUNTA(MakePayment!B59:B109) -> 51 | F7: =COUNTIF(MakePayment!D59:D109,"No Auto") -> 21 | G7: =COUNTIFS(MakePayment!D59:D109,"<>No Auto",MakePayment!D59:D109,"<>") -> 30 | H7: 30 | I7: =COUNTIF(MakePayment!SE$59:SE$109,"=In Progress") -> 0 | J7: =COUNTIF(MakePayment!$D$59:$D$109,"=QA Validation") -> 30
C8: Login | D8: Android | E8: =COUNTA(Login!B7:B14) -> 8 | F8: =COUNTIFS(Login!D7:D14,"No Auto") -> 8 | G8: =COUNTIFS(Login!D7:D14,"<>No Auto",Login!D7:D14,"<>") -> 0 | H8: - | I8: =COUNTIF(Login!$D$7:SE$14,"=In Progress") -> 0 | J8: =COUNTIF(Login!$D$7:$F$14,"=QA Validation") -> 0
D9: iOS | E9: =COUNTA(Login!B16:B23) -> 8 | F9: =COUNTIFS(Login!D16:D23,"No Auto") -> 8 | G9: =COUNTIFS(Login!D16:D23,"<>No Auto",Login!D16:D23,"<>") -> 0 | H9: - | I9: =COUNTIF(Login!$D$16:$D$23,"=In Progress") -> 0 | J9: =COUNTIF(Login!$D$16:$D$23,"=QA Validation") -> 0
C10: Outages | D10: Android | E10: =COUNTA(Outages!B7:B66) -> 60 | F10: =COUNTIF(Outages!D7:D66,"No Auto") -> 0 | G10: =COUNTIFS(Outages!D7:D66,"<>No Auto",Outages!D7:D66,"<>") -> 12 | H10: 60 | I10: =COUNTIF(Outages!$D$7:$D$66,"=In Progress") -> 0 | J10: =COUNTIF(Outages!$D$7:$D$66,"=QA Validation") -> 12
D11: iOS | E11: =COUNTA(Outages!B68:B128) -> 61 | F11: =COUNTIF(Outages!D68:D128,"No Auto") -> 18 | G11: =COUNTIFS(Outages!D68:D128,"<>No Auto",Outages!D68:D128,"<>") -> 43 | H11: =COUNTIF(Outages!$D$68:$D$128,"=In Progress") -> 0 | I11: =COUNTIF(Outages!$D$68:$D$128,"=In Progress") -> 0 | J11: =COUNTIF(Outages!$D$68:$D$128,"=QA Validation") -> 43
C12: Autopay | D12: Android | E12: =COUNTA(Autopay!B7:B30) -> 24 | F12: =COUNTIF(Autopay!D7:D30,"No Auto") -> 0 | G12: =COUNTIFS(Autopay!D7:D30,"<>No Auto",Autopay!D7:D30,"<>") -> 3 | H12: 24 | I12: =COUNTIF(Autopay!$D$7:$D$30,"=In Progress") -> 0 | J12: =COUNTIF(Autopay!$D$7:$D$30,"=QA Validation") -> 3
D13: iOS | E13: =COUNTA(Autopay!B32:B55) -> 24 | F13: =COUNTIF(Autopay!D32:D55,"No Auto") -> 0 | G13: =COUNTIFS(Autopay!D32:D55,"<>No Auto",Autopay!D32:D55,"<>") -> 24 | H13: =COUNTIF(Autopay!$D$32:$D$55,"=In Progress") -> 0 | I13: =COUNTIF(Autopay!$D$32:$D$55,"=In Progress") -> 0 | J13: =COUNTIF(Autopay!$D$32:$D$55,"=QA Validation") -> 24
G14: =SUM(G4:G13) -> 149 | I14: =SUM(I4:I13) -> 0 | J14: =SUM(J4:J13) -> 149 | K14: =SUM(K4:K13) -> 0
D17: Total No Auto | E17: =SUM(F4:F13) -> 70 | I17: Total TCs | J17: =E19-E17 -> 265
D18: Total Auto | E18: =SUM(G4:G13) -> 149 | I18: TCs Automated | J18: =J14+K14 -> 149
D19: Total | E19: =SUM(E4:E13) -> 335 | I19: Overall Progress | J19: =J18/J17 -> 0.56226415
B21: Billing&Payments | D21: My Preferences | I21: My Accounts
B22: Make a Payment | D22: Push Notifications | I22: Switch Accounts
B23: Enroll in e-Bill | D23: Alert Preferences | I23: Make a Payment
B24: View Bill | D24: e-Bill enroll/de-enroll | I24: My Preferences
B25: Download Bill | D25: Autopay enroll/de-enroll | I25: My Profile
B26: Cancel Payment | D26: Budget billing enroll/de-enroll (no cmp) | I26: Web Redirect
B27: View Bill/Payment History | D27: Operations ET enroll/de-enroll | I27: Lookout
D28: Biometrics | I28: Delete My Account
D29: Cash only enroll

Sheet ManagePayments
O1: June | AS1: July
A2: Manage Payment & Wallet | E2: F | F2: SA | G2: SU | H2: M | I2: T | J2: W | K2: Th | L2: F | M2: SA | N2: SU | O2: M | P2: T | Q2: W | R2: Th | S2: F | T2: SA | U2: SU | V2: M | W2: T | X2: W | Y2: Th | Z2: F | AA2: SA | AB2: SU | AC2: M | AD2: T | AE2: W | AF2: Th | AG2: F | AH2: SA | AI2: SU | AJ2: M | AK2: T | AL2: W | AM2: Th | AN2: F | AO2: SA | AP2: SU | AQ2: M | AR2: T | AS2: W | AT2: Th | AU2: F | AV2: SA | AW2: SU | AX2: M | AY2: T | AZ2: W | BA2: Th | BB2: F | BC2: SA | BD2: SU
E3: 22 | F3: 23 | G3: 24 | H3: 25 | I3: 26 | J3: 27 | K3: 28 | L3: 29 | M3: 30 | N3: 31 | O3: 1 | P3: 2 | Q3: 3 | R3: 4 | S3: 5 | T3: 6 | U3: 7 | V3: 8 | W3: 9 | X3: 10 | Y3: 11 | Z3: 12 | AA3: 13 | AB3: 14 | AC3: 15 | AD3: 16 | AE3: 17 | AF3: 18 | AG3: 19 | AH3: 20 | AI3: 21 | AJ3: 22 | AK3: 23 | AL3: 24 | AM3: 25 | AN3: 26 | AO3: 27 | AP3: 28 | AQ3: 29 | AR3: 30 | AS3: 1 | AT3: 2 | AU3: 3 | AV3: 4 | AW3: 5 | AX3: 6 | AY3: 7 | AZ3: 8 | BA3: 9 | BB3: 10 | BC3: 11 | BD3: 12
D4: CMP - iOS / Android
A5: TC Name | B5: TC Key | C5: Assigned To | D5: Status
A6: CMP - Android
A7: CMP - MNDC-624 - Android - Delete bin icon appears after swipe right | B7: MSTREG-T22756 | C7: Kevin | D7: QA Validation
A8: CMP - MNDC-624 - Android - Perform deletion by tapping bin icon (no Kubra wallet entry) | B8: MSTREG-T22757 | C8: Kevin | D8: QA Validation
A9: CMP - MNDC-624 - Android - Backend deletion API call is triggered and succeeds | B9: MSTREG-T22758 | C9: Kevin | D9: QA Validation
A10: CMP - MNDC-624 - Android - Delete a payment hidden when eBill flag is false | B10: MSTREG-T22759 | C10: Kevin | D10: QA Validation
A11: CMP - MNDC-614 - Android - Verify "Select payment method" section is visible when eBill = 'true' | B11: MSTREG-T22760 | C11: Kevin | D11: QA Validation
A12: CMP - MNDC-614 - Android - Verify "Select payment method" section is not visible when eBill = 'false' | B12: MSTREG-T22761 | C12: Kevin | D12: QA Validation
A13: CMP - MNDC-614 - Android - CMP/SCG-group: Stored payment methods present — "Manage payment methods" redirects to Kubra and shows Payment method screen with all buttons | B13: MSTREG-T22762 | C13: Kevin | D13: QA Validation
A14: CMP - MNDC-614 - Android - CMP/SCG-group: No stored payment methods — Only "Add bank account" and "Add credit or debit card" visible; Add credit/debit opens Kubra CC/DC view | B14: MSTREG-T22763 | C14: Kevin | D14: No Auto
A15: CMP - MNDC-614 - Android - CMP/SCG-group: No Stored payment methods — Add bank account opens Kubra bank-account view | B15: MSTREG-T22764 | C15: Kevin | D15: No Auto
A16: CMP - MNDC-614 - Android - CMP/UI opcos: Stored payment methods scenario — only "Add bank account" visible; Manage and Add card not shown; Add bank redirects to Kubra bank view | B16: MSTREG-T22765 | C16: Kevin | D16: No Auto
A17: CMP - MNDC-614 - Android - UI element visibility: "Manage my wallet" button visible (independent test) | B17: MSTREG-T22766 | C17: Kevin | D17: QA Validation
A18: CMP - MNDC-258 - Android - Display Payment Methods List Populated From API | B18: MSTREG-T22767 | C18: Kevin | D18: No Auto
... A30: CMP - MNDC-1583 - Android - Checking CC's availability and display icon on changing payment methods. | B30: MSTREG-T22800 | C30: Kevin | D30: QA Validation
A31: CMP - iOS
A32: CMP - MNDC-621 - IOS - Delete bin icon appears after swipe right | B32: MSTREG-T22777 | C32: Jimmy | D32: QA Validation
A33: CMP - MNDC-621 - IOS - Perform deletion by tapping bin icon (no Kubra wallet entry) | B33: MSTREG-T22778 | C33: Jimmy | D33: QA Validation
A34: CMP - MNDC-621 - IOS - Backend deletion API call is triggered and succeeds | B34: MSTREG-T22779 | C34: Jimmy | D34: No Auto
A35: CMP - MNDC-621 - IOS - Delete a payment hidden when eBill flag is false | B35: MSTREG-T22780 | C35: Jimmy | D35: QA Validation
A36: CMP - MNDC-613 - IOS - Verify "Select payment method" section is visible when eBill = 'true' | B36: MSTREG-T22781 | C36: Jimmy | D36: QA Validation
A37: CMP - MNDC-613 - IOS - Verify "Select payment method" section is not visible when eBill = 'false' | B37: MSTREG-T22782 | C37: Jimmy | D37: QA Validation
A38: CMP - MNDC-613 - IOS - CMP/CMP-group: Stored payment methods present — "Manage payment methods" redirects to Kubra and shows Payment method screen with all buttons | B38: MSTREG-T22783 | C38: Jimmy | D38: QA Validation
A39: CMP - MNDC-613 - IOS - CMP/CMP-group: No stored payment methods — Only "Add bank account" and "Add credit or debit card" visible; Add credit/debit opens Kubra CC/DC view | B39: MSTREG-T22784 | C39: Jimmy | D39: QA Validation
A40: CMP - MNDC-613 - IOS - CMP/CMP-group: No Stored payment methods — Add bank account opens Kubra bank-account view | B40: MSTREG-T22785 | C40: Jimmy | D40: QA Validation
A41: CMP - MNDC-613 - IOS - CMP/UI opcos: Stored payment methods scenario — only "Add bank account" visible; Manage and Add card not shown; Add bank redirects to Kubra bank view | B41: MSTREG-T22786 | C41: Jimmy | D41: QA Validation
A42: CMP - MNDC-613 - IOS - UI element visibility: "Manage my wallet" button visible (independent test) | B42: MSTREG-T22787 | C42: Jimmy | D42: QA Validation
A43: CMP - MNDC-390 - IOS - Display Payment Methods List Populated From API | B43: MSTREG-T22788 | C43: Jimmy | D43: No Auto
... A55: CMP - MNDC-1583 - iOS - Checking CC's availability and display icon on changing payment methods. | B55: MSTREG-T22803 | C55: Jimmy | D55: QA Validation

Sheet MakePayment
O1: June | AS1: July
A2: Make a Payment Flow | E2: F | F2: SA | G2: SU | H2: M | I2: T | J2: W | K2: Th | L2: F | M2: SA | N2: SU | O2: M | P2: T | Q2: W | R2: Th | S2: F | T2: SA | U2: SU | V2: M | W2: T | X2: W | Y2: Th | Z2: F | AA2: SA | AB2: SU | AC2: M | AD2: T | AE2: W | AF2: Th | AG2: F | AH2: SA | AI2: SU | AJ2: M | AK2: T | AL2: W | AM2: Th | AN2: F | AO2: SA | AP2: SU | AQ2: M | AR2: T | AS2: W | AT2: Th | AU2: F | AV2: SA | AW2: SU | AX2: M | AY2: T | AZ2: W | BA2: Th | BB2: F | BC2: SA | BD2: SU
E3: 22 | F3: 23 | G3: 24 | H3: 25 | I3: 26 | J3: 27 | K3: 28 | L3: 29 | M3: 30 | N3: 31 | O3: 1 | P3: 2 | Q3: 3 | R3: 4 | S3: 5 | T3: 6 | U3: 7 | V3: 8 | W3: 9 | X3: 10 | Y3: 11 | Z3: 12 | AA3: 13 | AB3: 14 | AC3: 15 | AD3: 16 | AE3: 17 | AF3: 18 | AG3: 19 | AH3: 20 | AI3: 21 | AJ3: 22 | AK3: 23 | AL3: 24 | AM3: 25 | AN3: 26 | AO3: 27 | AP3: 28 | AQ3: 29 | AR3: 30 | AS3: 1 | AT3: 2 | AU3: 3 | AV3: 4 | AW3: 5 | AX3: 6 | AY3: 7 | AZ3: 8 | BA3: 9 | BB3: 10 | BC3: 11 | BD3: 12
D4: CMP - iOS / Android
A5: TC Name | B5: TC Key | C5: Assigned To | D5: Status
A6: CMP - Android
A7: MNDC-1837 - CMP - Android - Access Make a payment from Bills & Payments for eBill account | B7: MSTREG-T22473
A8: MNDC-1837 - CMP - Android - Access Make a payment from Home widget for eBill account | B8: MSTREG-T22474
A9: MNDC-1837 - CMP - Android - Access Make a payment from Account > Make a payment | B9: MSTREG-T22475
A10: MNDC-1837 - CMP - Android - Make a payment flow visible only when eBill = true | B10: MSTREG-T22476
A11: MNDC-1837 - CMP - Android - At least one payment method saved – list and selection | B11: MSTREG-T22477
A12: MNDC-1837 - CMP - Android - Payment amount defaulted to Amount due in normal billing period | B12: MSTREG-T22478
A13: MNDC-1837 - CMP - Android - Payment amount shows total balance for payment plan or budget billing | B13: MSTREG-T22479
A14: MNDC-1837 - CMP - Android - Payment amount not editable for Past Due accounts | B14: MSTREG-T22480
A15: MNDC-1837 - CMP - Android - Payment amount not editable for Final Termination Notice accounts | B15: MSTREG-T22481
A16: MNDC-1837 - CMP - Android - Payment date defaults to Today and editable for normal billing | B16: MSTREG-T22482
A17: MNDC-1837 - CMP - Android - Payment date not schedulable for Past Due accounts | B17: MSTREG-T22483
A18: MNDC-1837 - CMP - Android - Payment date not schedulable for Final Termination Notice accounts | B18: MSTREG-T22484
... A49: CMP - MNDC-1837 - Android - Cash nonRes | B49: MSTREG-T22515
A50: CMP - MNDC-279 - Android - Non eBill - New ACH Payment with Bank Account Selected | B50: MSTREG-T22567 | D50: No Auto
A51: CMP - MNDC-279 - Android - Non eBill - Existing ACH Payment (Remember Me) - Display Stored Payment Methods | B51: MSTREG-T22568
A52: CMP - MNDC-279 - Android - Non eBill - New Credit/Debit Card Payment | B52: MSTREG-T22569 | D52: No Auto
A53: CMP - MNDC-279 - Android - Non eBill - Existing Credit/Debit Card Payment - Display Stored Payment Methods | B53: MSTREG-T22570
A54: CMP - MNDC-279 - Android - eBill - Payemnt with New ACH Payment with Bank Account Selected | B54: MSTREG-T22571 | D54: No Auto
A55: CMP - MNDC-279 - Android - eBill - Payment with existing ACH Payment | B55: MSTREG-T22572
A56: CMP - MNDC-279 - Android - eBill - Payment with ew Credit/Debit Card Payment | B56: MSTREG-T22573 | D56: No Auto
A57: CMP - MNDC-279 - Android - eBill - Payment with existing Credit/Debit Card Payment | B57: MSTREG-T22574
A58: CMP - iOS
A59: MNDC-1834 - CMP - IOS - Access Make a payment from Bills & Payments for eBill account | B59: MSTREG-T22516 | C59: Nicolas | D59: QA Validation
A60: MNDC-1834 - CMP - IOS - Access Make a payment from Home widget for eBill account | B60: MSTREG-T22517 | C60: Nicolas | D60: QA Validation
A61: MNDC-1834 - CMP - IOS - Access Make a payment from Account > Make a payment | B61: MSTREG-T22518 | C61: Nicolas | D61: QA Validation
A62: MNDC-1834 - CMP - IOS - Make a payment flow visible only when eBill = true | B62: MSTREG-T22519 | C62: Nicolas | D62: QA Validation
A63: MNDC-1834 - CMP - IOS - At least one payment method saved – list and selection | B63: MSTREG-T22520 | C63: Nicolas | D63: QA Validation
A64: MNDC-1834 - CMP - IOS - Payment amount defaulted to Amount due in normal billing period | B64: MSTREG-T22521 | C64: Nicolas | D64: QA Validation
A65: MNDC-1834 - CMP - IOS - Payment amount shows total balance for payment plan or budget billing | B65: MSTREG-T22522 | C65: Nicolas | D65: QA Validation
A66: MNDC-1834 - CMP - IOS - Payment amount not editable for Past Due accounts | B66: MSTREG-T22523 | C66: Nicolas | D66: No Auto
A67: MNDC-1834 - CMP - IOS - Payment amount not editable for Final Termination Notice accounts | B67: MSTREG-T22524 | C67: Nicolas | D67: No Auto
A68: MNDC-1834 - CMP - IOS - Payment date defaults to Today and editable for normal billing | B68: MSTREG-T22525 | C68: Nicolas | D68: No Auto
A69: MNDC-1834 - CMP - IOS - Payment date not schedulable for Past Due accounts | B69: MSTREG-T22526 | C69: Nicolas | D69: QA Validation
A70: MNDC-1834 - CMP - IOS - Payment date not schedulable for Final Termination Notice accounts | B70: MSTREG-T22527 | C70: Nicolas | D70: No Auto
... A109: CMP - MNDC-279 - IOS - eBill - Payment with existing Credit/Debit Card Payment | B109: MSTREG-T22566 | C109: Nicolas | D109: QA Validation

Sheet Login
O1: June | AS1: July
A2: Login | E2: F | F2: SA | G2: SU | H2: M | I2: T | J2: W | K2: Th | L2: F | M2: SA | N2: SU | O2: M | P2: T | Q2: W | R2: Th | S2: F | T2: SA | U2: SU | V2: M | W2: T | X2: W | Y2: Th | Z2: F | AA2: SA | AB2: SU | AC2: M | AD2: T | AE2: W | AF2: Th | AG2: F | AH2: SA | AI2: SU | AJ2: M | AK2: T | AL2: W | AM2: Th | AN2: F | AO2: SA | AP2: SU | AQ2: M | AR2: T | AS2: W | AT2: Th | AU2: F | AV2: SA | AW2: SU | AX2: M | AY2: T | AZ2: W | BA2: Th | BB2: F | BC2: SA | BD2: SU
E3: 22 | F3: 23 | G3: 24 | H3: 25 | I3: 26 | J3: 27 | K3: 28 | L3: 29 | M3: 30 | N3: 31 | O3: 1 | P3: 2 | Q3: 3 | R3: 4 | S3: 5 | T3: 6 | U3: 7 | V3: 8 | W3: 9 | X3: 10 | Y3: 11 | Z3: 12 | AA3: 13 | AB3: 14 | AC3: 15 | AD3: 16 | AE3: 17 | AF3: 18 | AG3: 19 | AH3: 20 | AI3: 21 | AJ3: 22 | AK3: 23 | AL3: 24 | AM3: 25 | AN3: 26 | AO3: 27 | AP3: 28 | AQ3: 29 | AR3: 30 | AS3: 1 | AT3: 2 | AU3: 3 | AV3: 4 | AW3: 5 | AX3: 6 | AY3: 7 | AZ3: 8 | BA3: 9 | BB3: 10 | BC3: 11 | BD3: 12
D4: CMP - iOS / Android
A5: TC Name | B5: TC Key | C5: Assigned To | D5: Status
A6: CMP - Android
A7: CMP - IOS - First-Time Login - Enable Biometric Setup (Happy Path) | B7: MSTREG-T22743 | D7: No Auto
A8: CMP - IOS - First-Time Login - Decline / Cancel Biometric Setup | B8: MSTREG-T22744 | D8: No Auto
A9: CMP - IOS - Returning User - Successful Biometric Login (Cold Start & Auto-Prompt) | B9: MSTREG-T22745 | D9: No Auto
A10: CMP - IOS - Biometric Failure - Retry - Repeated Failure - Manual Fallback | B10: MSTREG-T22746 | D10: No Auto
A11: CMP - IOS - Biometric Not Available - Device and System Level Issues | B11: MSTREG-T22747 | D11: No Auto
A12: CMP - IOS - Biometric Edge Cases - Timeout, Multi-User, Cancel Prompt, Warm Start | B12: MSTREG-T22748 | D12: No Auto
A13: CMP - IOS - Session Timeout - Notification and Biometric Re-authentication | B13: MSTREG-T22749 | D13: No Auto
A14: CMP - IOS - Ionic to Native App Upgrade - Biometric Continuity | B14: MSTREG-T22750 | D14: No Auto
A15: CMP - iOS
A16: CMP - IOS - First-Time Login - Enable Biometric Setup (Happy Path) | B16: MSTREG-T22743 | D16: No Auto
A17: CMP - IOS - First-Time Login - Decline / Cancel Biometric Setup | B17: MSTREG-T22744 | D17: No Auto
A18: CMP - IOS - Returning User - Successful Biometric Login (Cold Start & Auto-Prompt) | B18: MSTREG-T22745 | D18: No Auto
A19: CMP - IOS - Biometric Failure - Retry - Repeated Failure - Manual Fallback | B19: MSTREG-T22746 | D19: No Auto
A20: CMP - IOS - Biometric Not Available - Device and System Level Issues | B20: MSTREG-T22747 | D20: No Auto
A21: CMP - IOS - Biometric Edge Cases - Timeout, Multi-User, Cancel Prompt, Warm Start | B21: MSTREG-T22748 | D21: No Auto
A22: CMP - IOS - Session Timeout - Notification and Biometric Re-authentication | B22: MSTREG-T22749 | D22: No Auto
A23: CMP - IOS - Ionic to Native App Upgrade - Biometric Continuity | B23: MSTREG-T22750 | D23: No Auto

Sheet Autopay
O1: June | AS1: July | BE1: July
A2: Autopay | E2: F | F2: SA | G2: SU | H2: M | I2: T | J2: W | K2: Th | L2: F | M2: SA | N2: SU | O2: M | P2: T | Q2: W | R2: Th | S2: F | T2: SA | U2: SU | V2: M | W2: T | X2: W | Y2: Th | Z2: F | AA2: SA | AB2: SU | AC2: M | AD2: T | AE2: W | AF2: Th | AG2: F | AH2: SA | AI2: SU | AJ2: M | AK2: T | AL2: W | AM2: Th | AN2: F | AO2: SA | AP2: SU | AQ2: M | AR2: T | AS2: W | AT2: Th | AU2: F | AV2: SA | AW2: SU | AX2: M | AY2: T | AZ2: W | BA2: Th | BB2: F | BC2: SA | BD2: SU | BE2: M | BF2: T | BG2: W | BH2: Th | BI2: F | BJ2: SA | BK2: SU
E3: 22 | F3: 23 | G3: 24 | H3: 25 | I3: 26 | J3: 27 | K3: 28 | L3: 29 | M3: 30 | N3: 31 | O3: 1 | P3: 2 | Q3: 3 | R3: 4 | S3: 5 | T3: 6 | U3: 7 | V3: 8 | W3: 9 | X3: 10 | Y3: 11 | Z3: 12 | AA3: 13 | AB3: 14 | AC3: 15 | AD3: 16 | AE3: 17 | AF3: 18 | AG3: 19 | AH3: 20 | AI3: 21 | AJ3: 22 | AK3: 23 | AL3: 24 | AM3: 25 | AN3: 26 | AO3: 27 | AP3: 28 | AQ3: 29 | AR3: 30 | AS3: 1 | AT3: 2 | AU3: 3 | AV3: 4 | AW3: 5 | AX3: 6 | AY3: 7 | AZ3: 8 | BA3: 9 | BB3: 10 | BC3: 11 | BD3: 12 | BE3: 13 | BF3: 14 | BG3: 15 | BH3: 16 | BI3: 17 | BJ3: 18 | BK3: 19
D4: CMP - iOS / Android
A5: TC Name | B5: TC Key | C5: Assigned To | D5: Status
A6: CMP - Android
A7: MNDC-2174 - CMP - Android - Feature is visible only when Account is CMP and eBill = true and Autopay = false | B7: MSTREG-T22575 | C7: Jimmy | D7: QA Validation
A8: MNDC-2174 - CMP - Android - Feature hidden when eBill=false even if CMP=true | B8: MSTREG-T22576 | C8: Jimmy | D8: QA Validation
A9: MNDC-2174 - CMP - Android - Attempt to add Credit Card is blocked for CMP eBill user | B9: MSTREG-T22577 | C9: Jimmy | D9: QA Validation
A10: MNDC-2174 - CMP - Android - Empty state when no payment method exists | B10: MSTREG-T22578 | C10: Jimmy
A11: MNDC-2174 - CMP - Android - Existing bank account is displayed when present | B11: MSTREG-T22579 | C11: Jimmy
A12: MNDC-2174 - CMP - Android - Schedule AutoPay label and helper text are present | B12: MSTREG-T22580 | C12: Jimmy
A13: MNDC-2174 - CMP - Android - Schedule dropdown default value = 10 | B13: MSTREG-T22581 | C13: Jimmy
A14: MNDC-2174 - CMP - Android - Schedule dropdown allowed range 5–23 inclusive | B14: MSTREG-T22582 | C14: Jimmy
A15: MNDC-2174 - CMP - Android - Payment Amount minimum = $1.00 with error below minimum | B15: MSTREG-T22583 | C15: Jimmy
A16: MNDC-2174 - CMP - Android - Payment Amount maximum = $99,999.99 with error above maximum | B16: MSTREG-T22584 | C16: Jimmy
A17: MNDC-2174 - CMP - Android - Payment Amount accepts boundary values $1.00 and $99,999.99 | B17: MSTREG-T22585 | C17: Jimmy
A18: MNDC-2174 - CMP - Android - Payment Amount rejects non-numeric and too many decimals | B18: MSTREG-T22586 | C18: Jimmy
A19: MNDC-2174 - CMP - Android - Successful enrollment with existing bank account | B19: MSTREG-T22587 | C19: Jimmy
A20: MNDC-2174 - CMP - Android - Successful enrollment by adding a new bank account during flow | B20: MSTREG-T22588 | C20: Jimmy
A21: MNDC-2174 - CMP - Android - Attempt to enroll without selecting/adding a bank account | B21: MSTREG-T22589 | C21: Jimmy
... A30: MNDC-2174 - CMP - Android - Confirmation screen appears after successful validation and enrollment | B30: MSTREG-T22598 | C30: Jimmy
A31: CMP - iOS
A32: MNDC-2173 - CMP - IOS - Feature is visible only when Account is CMP and eBill = true and Autopay = false | B32: MSTREG-T22599 | C32: Jimmy | D32: QA Validation
A33: MNDC-2173 - CMP - IOS - Feature hidden when eBill=false even if CMP=true | B33: MSTREG-T22600 | C33: Jimmy | D33: QA Validation
A34: MNDC-2173 - CMP - IOS - Attempt to add Credit Card is blocked for CMP eBill user | B34: MSTREG-T22601 | C34: Jimmy | D34: QA Validation
A35: MNDC-2173 - CMP - IOS - Empty state when no payment method exists | B35: MSTREG-T22602 | C35: Jimmy | D35: QA Validation
A36: MNDC-2173 - CMP - IOS - Existing bank account is displayed when present | B36: MSTREG-T22603 | C36: Jimmy | D36: QA Validation
A37: MNDC-2173 - CMP - IOS - Schedule AutoPay label and helper text are present | B37: MSTREG-T22604 | C37: Jimmy | D37: QA Validation
A38: MNDC-2173 - CMP - IOS - Schedule dropdown default value = 10 | B38: MSTREG-T22605 | C38: Jimmy | D38: QA Validation
A39: MNDC-2173 - CMP - IOS - Schedule dropdown allowed range 5–23 inclusive | B39: MSTREG-T22606 | C39: Jimmy | D39: QA Validation
A40: MNDC-2173 - CMP - IOS - Payment Amount minimum = $1.00 with error below minimum | B40: MSTREG-T22607 | C40: Jimmy | D40: QA Validation
A41: MNDC-2173 - CMP - IOS - Payment Amount maximum = $99,999.99 with error above maximum | B41: MSTREG-T22608 | C41: Jimmy | D41: QA Validation
A42: MNDC-2173 - CMP - IOS - Payment Amount accepts boundary values $1.00 and $99,999.99 | B42: MSTREG-T22609 | C42: Jimmy | D42: QA Validation
A43: MNDC-2173 - CMP - IOS - Payment Amount rejects non-numeric and too many decimals | B43: MSTREG-T22610 | C43: Jimmy | D43: QA Validation
... A55: End Autopay | B55: EXTRA | C55: Jimmy | D55: QA Validation

Sheet Outages
O1: June | AS1: July
A2: Outages | E2: F | F2: SA | G2: SU | H2: M | I2: T | J2: W | K2: Th | L2: F | M2: SA | N2: SU | O2: M | P2: T | Q2: W | R2: Th | S2: F | T2: SA | U2: SU | V2: M | W2: T | X2: W | Y2: Th | Z2: F | AA2: SA | AB2: SU | AC2: M | AD2: T | AE2: W | AF2: Th | AG2: F | AH2: SA | AI2: SU | AJ2: M | AK2: T | AL2: W | AM2: Th | AN2: F | AO2: SA | AP2: SU | AQ2: M | AR2: T | AS2: W | AT2: Th | AU2: F | AV2: SA | AW2: SU | AX2: M | AY2: T | AZ2: W | BA2: Th | BB2: F | BC2: SA | BD2: SU | BE2: M | BF2: T | BG2: W | BH2: Th | BI2: F | BJ2: SA | BK2: SU | BL2: M | BM2: T | BN2: W | BO2: Th | BP2: F | BQ2: SA | BR2: SU | BS2: M | BT2: T | BU2: W | BV2: Th | BW2: F | BX2: SA | BY2: SU
E3: 22 | F3: 23 | G3: 24 | H3: 25 | I3: 26 | J3: 27 | K3: 28 | L3: 29 | M3: 30 | N3: 31 | O3: 1 | P3: 2 | Q3: 3 | R3: 4 | S3: 5 | T3: 6 | U3: 7 | V3: 8 | W3: 9 | X3: 10 | Y3: 11 | Z3: 12 | AA3: 13 | AB3: 14 | AC3: 15 | AD3: 16 | AE3: 17 | AF3: 18 | AG3: 19 | AH3: 20 | AI3: 21 | AJ3: 22 | AK3: 23 | AL3: 24 | AM3: 25 | AN3: 26 | AO3: 27 | AP3: 28 | AQ3: 29 | AR3: 30 | AS3: 1 | AT3: 2 | AU3: 3 | AV3: 4 | AW3: 5 | AX3: 6 | AY3: 7 | AZ3: 8 | BA3: 9 | BB3: 10 | BC3: 11 | BD3: 12 | BE3: 13 | BF3: 14 | BG3: 15 | BH3: 16 | BI3: 17 | BJ3: 18 | BK3: 19 | BL3: 20 | BM3: 21 | BN3: 22 | BO3: 23 | BP3: 24 | BQ3: 25 | BR3: 26 | BS3: 27 | BT3: 28 | BU3: 29 | BV3: 30 | BW3: 31 | BX3: 32 | BY3: 33
D4: CMP - iOS / Android
A5: TC Name | B5: TC Key | C5: Assigned To | D5: Status
A6: CMP - Android
A7: CMP - MNDC-111 - Android - Outage List opens in in-app web with SSO (CMP) | B7: MSTREG-T22622 | C7: Nicolas | D7: QA Validation
A8: CMP - MNDC-111 - Android - Outage Map opens in in-app web (CMP) | B8: MSTREG-T22623 | C8: Nicolas | D8: QA Validation
A9: CMP - MNDC-111 - Android - Outage Central redirects to CMP outages landing with SSO | B9: MSTREG-T22624 | C9: Nicolas | D9: QA Validation
A10: CMP - MNDC-111 - Android - Facebook opens native app for CMP if installed | B10: MSTREG-T22625 | C10: Nicolas | D10: QA Validation
A11: CMP - MNDC-111 - Android - Facebook falls back to in-app webview for CMP if not installed | B11: MSTREG-T22626 | C11: Nicolas | D11: QA Validation
A12: CMP - MNDC-111 - Android - Instagram opens native app for CMP if installed | B12: MSTREG-T22627 | C12: Nicolas | D12: QA Validation
A13: CMP - MNDC-111 - Android - Instagram falls back to in-app webview for CMP if not installed | B13: MSTREG-T22628 | C13: Nicolas | D13: QA Validation
A14: CMP - MNDC-111 - Android - X opens native app for CMP if installed | B14: MSTREG-T22629 | C14: Nicolas | D14: QA Validation
A15: CMP - MNDC-111 - Android - X falls back to in-app webview for CMP if not installed | B15: MSTREG-T22630 | C15: Nicolas | D15: QA Validation
A16: CMP - MNDC-111 - Android - Call 911 - Confirm Dialog, Cancel, and Call Behavior | B16: MSTREG-T22631 | C16: Nicolas | D16: QA Validation
A17: CMP – MNDC-2062 – Android – Outage tab visible for authenticated CMP electric user | B17: MSTREG-T22659
A18: CMP – MNDC-2062 – Android – Outage tab hidden or requires auth when logged out | B18: MSTREG-T22660 | C18: Nicolas | D18: QA Validation
A19: CMP – MNDC-2062 – Android – ‘Outage’ tab selected state is green (per Figma) | B19: MSTREG-T22661
A20: CMP – MNDC-2062 – Android – Outage modules present (CMP) | B20: MSTREG-T22662
A21: CMP – MNDC-2062 – Android – Outage Banner reflects CMP service address state | B21: MSTREG-T22663
A22: CMP – MNDC-2062 – Android – Outage List opens in in-app web with SSO (CMP) | B22: MSTREG-T22664
A23: CMP – MNDC-2062 – Android – Outage Map opens in in-app web (CMP) | B23: MSTREG-T22665
A24: CMP – MNDC-2062 – Android – Outage Central redirects to CMP outages landing with SSO | B24: MSTREG-T22666
A25: CMP – MNDC-2062 – Android – Outage Alerts opens My Preferences > Outage Alerts (CMP) | B25: MSTREG-T22667
A26: CMP – MNDC-2062 – Android – Outage Alerts requires auth if session expired (CMP) | B26: MSTREG-T22668 | C26: Nicolas | D26: QA Validation
A27: CMP – MNDC-2062 – Android – Facebook opens native app for CMP if installed | B27: MSTREG-T22669
A28: CMP – MNDC-2062 – Android – Facebook falls back to in-app webview for CMP if not installed | B28: MSTREG-T22670
A29: CMP – MNDC-2062 – Android – Instagram opens native app for CMP if installed | B29: MSTREG-T22671
A30: CMP – MNDC-2062 – Android – Instagram falls back to in-app webview for CMP if not installed | B30: MSTREG-T22672
A31: CMP – MNDC-2062 – Android – X opens native app for CMP if installed | B31: MSTREG-T22673
A32: CMP – MNDC-2062 – Android – X falls back to in-app webview for CMP if not installed | B32: MSTREG-T22674
A33: CMP – MNDC-2062 – Android – Call 911 – Confirm Dialog, Cancel, and Call Behavior | B33: MSTREG-T22675
A34: CMP – MNDC‑2108 – Android – Verify banner visible only for electric accounts | B34: MSTREG-T22685
A35: CMP – MNDC‑2108 – Android – Verify banner hidden for non‑electric accounts | B35: MSTREG-T22686
A36: CMP – MNDC‑2108 – Android – Verify scrolling behavior | B36: MSTREG-T22687
A37: CMP – MNDC‑2108 – Android – Verify account switch behavior | B37: MSTREG-T22688
A38: CMP – MNDC‑2108 – Android – No reported outage — Green pill | B38: MSTREG-T22689
... A66: MNDC -194 - CMP - Android - Re-display promo after app reinstall | B66: MSTREG-T22742
A67: CMP - iOS
A68: CMP - MNDC-104 - IOS - Outage List opens in in-app web with SSO (CMP) | B68: MSTREG-T22632 | C68: Jimmy | D68: QA Validation
A69: CMP - MNDC-104 - IOS - Outage Map opens in in-app web (CMP) | B69: MSTREG-T22633 | C69: Jimmy | D69: QA Validation
A70: CMP - MNDC-104 - IOS - Outage Central redirects to CMP outages landing with SSO | B70: MSTREG-T22634 | C70: Jimmy | D70: QA Validation
A71: CMP - MNDC-104 - IOS - Facebook opens native app for CMP if installed | B71: MSTREG-T22635 | C71: Jimmy | D71: No Auto
A72: CMP - MNDC-104 - IOS - Facebook falls back to in-app webview for CMP if not installed | B72: MSTREG-T22636 | C72: Jimmy | D72: QA Validation
A73: CMP - MNDC-104 - IOS - Instagram opens native app for CMP if installed | B73: MSTREG-T22637 | C73: Jimmy | D73: No Auto
A74: CMP - MNDC-104 - IOS - Instagram falls back to in-app webview for CMP if not installed | B74: MSTREG-T22638 | C74: Jimmy | D74: QA Validation
A75: CMP - MNDC-104 - IOS - X opens native app for CMP if installed | B75: MSTREG-T22639 | C75: Jimmy | D75: No Auto
A76: CMP - MNDC-104 - IOS - X falls back to in-app webview for CMP if not installed | B76: MSTREG-T22640 | C76: Jimmy | D76: QA Validation
A77: CMP - MNDC-104 - IOS - Call 911 - Confirm Dialog, Cancel, and Call Behavior | B77: MSTREG-T22641 | C77: Jimmy | D77: QA Validation
A78: CMP – MNDC-2061 – iOS – Outage tab visible for authenticated CMP electric user | B78: MSTREG-T22642 | C78: Jimmy | D78: QA Validation
A79: CMP – MNDC-2061 – iOS – Outage tab hidden or requires auth when logged out | B79: MSTREG-T22643 | C79: Jimmy | D79: QA Validation
... A128: MNDC -148 - CMP - IOS - Re-display promo after app reinstall | B128: MSTREG-T22727 | C128: Jimmy | D128: No Auto

Sheet Release Calendar
B2: OPCO | C2: Deployment
B3: CNG - iOS | C3: 45930
B4: CNG - Android | C4: 46079
B5: SCG - iOS | C5: 45929
B6: SCG - Android | C6: 46079
B7: BGC - iOS | C7: 46098
B8: BGC - Android | C8: 46098
B9: UI - iOS | C9: 46198
B10: UI - Android | C10: 46198
B11: CMP - iOS | C11: 46128
B12: CMP - Android | C12: 46128
B13: NYSEG - iOS | C13: 46149
B14: NYSEG - Android | C14: 46149
... B16: RGE - Android | C16: 46170
